{"v":"5.9.6","fr":25,"ip":0,"op":250,"w":1920,"h":1280,"nm":"Slide1-short","ddd":0,"assets":[],"fonts":{"list":[{"fName":"Inter-Medium","fFamily":"Inter","fStyle":"Medium","ascent":92.7264404296875}]},"layers":[{"ddd":0,"ind":1,"ty":5,"nm":"current  price","parent":3,"sr":1,"ks":{"o":{"a":0,"k":100},"r":{"a":0,"k":0},"p":{"s":true,"x":{"a":0,"k":24},"y":{"a":1,"k":[{"i":{"x":[0.256],"y":[1]},"o":{"x":[0.333],"y":[0]},"t":117,"s":[-171]},{"i":{"x":[0.667],"y":[1]},"o":{"x":[0.167],"y":[0]},"t":135,"s":[-340]},{"i":{"x":[0.311],"y":[1]},"o":{"x":[0.333],"y":[0]},"t":230,"s":[-340]},{"t":248,"s":[-171]}]}},"a":{"a":0,"k":[0,0,0]},"s":{"a":0,"k":[100,100,100]}},"ao":0,"t":{"d":{"k":[{"s":{"s":30,"f":"Inter-Medium","t":"current \rprice","ca":0,"j":0,"tr":-3,"lh":31,"ls":0,"fc":[0.808,0.784,0.953],"sc":[0,0,0],"sw":0.00999999977648,"of":false},"t":0}]},"p":{},"m":{"g":1,"a":{"a":0,"k":[0,0]}},"a":[]},"ip":0,"op":775,"st":0,"ct":1,"bm":0},{"ddd":0,"ind":2,"ty":5,"nm":"current  price 2","parent":1,"sr":1,"ks":{"o":{"a":1,"k":[{"i":{"x":[0.667],"y":[1]},"o":{"x":[0.333],"y":[0]},"t":0,"s":[0]},{"i":{"x":[0.667],"y":[1]},"o":{"x":[0.333],"y":[0]},"t":15,"s":[70]},{"i":{"x":[0.667],"y":[1]},"o":{"x":[0.167],"y":[0]},"t":35,"s":[0]},{"i":{"x":[0.667],"y":[1]},"o":{"x":[0.333],"y":[0]},"t":85,"s":[0]},{"i":{"x":[0.667],"y":[1]},"o":{"x":[0.333],"y":[0]},"t":100,"s":[70]},{"i":{"x":[0.667],"y":[1]},"o":{"x":[0.333],"y":[0]},"t":120,"s":[0]},{"i":{"x":[0.667],"y":[1]},"o":{"x":[0.333],"y":[0]},"t":170,"s":[0]},{"i":{"x":[0.667],"y":[1]},"o":{"x":[0.333],"y":[0]},"t":185,"s":[70]},{"t":205,"s":[0]}]},"r":{"a":0,"k":0},"p":{"s":true,"x":{"a":0,"k":0},"y":{"a":0,"k":0}},"a":{"a":0,"k":[0,0,0]},"s":{"a":0,"k":[100,100,100]}},"ao":0,"ef":[{"ty":29,"nm":"Gaussian Blur","np":5,"mn":"ADBE Gaussian Blur 2","ix":1,"en":1,"ef":[{"ty":0,"nm":"Blurriness","mn":"ADBE Gaussian Blur 2-0001","ix":1,"v":{"a":0,"k":14.8}},{"ty":7,"nm":"Blur Dimensions","mn":"ADBE Gaussian Blur 2-0002","ix":2,"v":{"a":0,"k":1}},{"ty":7,"nm":"Repeat Edge Pixels","mn":"ADBE Gaussian Blur 2-0003","ix":3,"v":{"a":0,"k":0}}]}],"t":{"d":{"k":[{"s":{"s":30,"f":"Inter-Medium","t":"current \rprice","ca":0,"j":0,"tr":-3,"lh":31,"ls":0,"fc":[1,1,1],"sc":[0,0,0],"sw":0.00999999977648,"of":false},"t":0}]},"p":{},"m":{"g":1,"a":{"a":0,"k":[0,0]}},"a":[]},"ip":0,"op":775,"st":0,"ct":1,"bm":0},{"ddd":0,"ind":3,"ty":4,"nm":"price line","sr":1,"ks":{"o":{"a":0,"k":100},"r":{"a":0,"k":0},"p":{"s":true,"x":{"a":1,"k":[{"i":{"x":[0.455],"y":[1]},"o":{"x":[0.513],"y":[0]},"t":0,"s":[951.335]},{"i":{"x":[0.667],"y":[1]},"o":{"x":[0.513],"y":[0]},"t":60,"s":[1143.335]},{"i":{"x":[0.576],"y":[1]},"o":{"x":[0.513],"y":[0]},"t":115,"s":[951.335]},{"i":{"x":[0.667],"y":[1]},"o":{"x":[0.348],"y":[0]},"t":175,"s":[866.335]},{"t":250,"s":[951.335]}]},"y":{"a":0,"k":645}},"a":{"a":0,"k":[0,0,0]},"s":{"a":0,"k":[100,100,100]}},"ao":0,"ef":[{"ty":5,"nm":"Slider Control","np":3,"mn":"ADBE Slider Control","ix":1,"en":1,"ef":[{"ty":0,"nm":"Slider","mn":"ADBE Slider Control-0001","ix":1,"v":{"a":0,"k":0,"x":"var $bm_rt;\n$bm_rt = transform.xPosition;"}}]}],"shapes":[{"ty":"gr","it":[{"ind":0,"ty":"sh","ks":{"a":1,"k":[{"i":{"x":0.833,"y":1},"o":{"x":0.333,"y":0},"t":0,"s":[{"i":[[0,0],[0,0]],"o":[[0,0],[0,0]],"v":[[5.875,-184.5],[5.75,178]],"c":false}]},{"i":{"x":0.256,"y":1},"o":{"x":0.333,"y":0},"t":117,"s":[{"i":[[0,0],[0,0]],"o":[[0,0],[0,0]],"v":[[5.875,-184.5],[5.75,178]],"c":false}]},{"i":{"x":0.667,"y":1},"o":{"x":0.167,"y":0},"t":135,"s":[{"i":[[0,0],[0,0]],"o":[[0,0],[0,0]],"v":[[5.704,-350.5],[5.812,178]],"c":false}]},{"i":{"x":0.311,"y":1},"o":{"x":0.333,"y":0},"t":230,"s":[{"i":[[0,0],[0,0]],"o":[[0,0],[0,0]],"v":[[5.704,-350.5],[5.812,178]],"c":false}]},{"t":248,"s":[{"i":[[0,0],[0,0]],"o":[[0,0],[0,0]],"v":[[5.875,-184.5],[5.75,178]],"c":false}]}]},"nm":"Path 1","hd":false},{"ty":"st","c":{"a":0,"k":[0.707147695504,0.673648609835,0.913725490196,1]},"o":{"a":0,"k":100},"w":{"a":0,"k":11},"lc":2,"lj":1,"ml":4,"bm":0,"d":[{"n":"d","nm":"dash","v":{"a":0,"k":24}},{"n":"o","nm":"offset","v":{"a":0,"k":0}}],"nm":"Stroke 1","hd":false},{"ty":"tr","p":{"a":0,"k":[0,0]},"a":{"a":0,"k":[0,0]},"s":{"a":0,"k":[100,100]},"r":{"a":0,"k":0},"o":{"a":0,"k":100},"sk":{"a":0,"k":0},"sa":{"a":0,"k":0},"nm":"Transform"}],"nm":"Shape 1","bm":0,"hd":false}],"ip":0,"op":775,"st":0,"ct":1,"bm":0},{"ddd":0,"ind":4,"ty":4,"nm":"18","sr":1,"ks":{"o":{"a":0,"k":50},"r":{"a":0,"k":0},"p":{"a":0,"k":[1553,823.75,0]},"a":{"a":0,"k":[-629.25,162.75,0]},"s":{"a":1,"k":[{"i":{"x":[0.667,0.667,0.667],"y":[0.93,2.024,1]},"o":{"x":[0.333,0.333,0.333],"y":[0,0,0]},"t":98,"s":[100,100,100]},{"i":{"x":[0.651,0.49,0.667],"y":[1,1,1]},"o":{"x":[0.341,0.548,0.333],"y":[0.143,0.164,0]},"t":103,"s":[100,105,100]},{"i":{"x":[0.667,0.667,0.667],"y":[1,1,1]},"o":{"x":[0.167,0.167,0.167],"y":[0,0,0]},"t":113,"s":[100,2,100]},{"i":{"x":[0.311,0.301,0.667],"y":[1,1,1]},"o":{"x":[0.333,0.333,0.333],"y":[0,0,0]},"t":230,"s":[100,2,100]},{"t":248,"s":[100,100,100]}]}},"ao":0,"shapes":[{"ty":"gr","it":[{"ty":"rc","d":1,"s":{"a":0,"k":[64,101.053]},"p":{"a":0,"k":[0,0]},"r":{"a":0,"k":0},"nm":"Rectangle Path 1","hd":false},{"ty":"st","c":{"a":0,"k":[0.231372563979,0.211764720842,0.423529441684,1]},"o":{"a":0,"k":100},"w":{"a":0,"k":0},"lc":1,"lj":1,"ml":4,"bm":0,"nm":"Stroke 1","hd":false},{"ty":"fl","c":{"a":0,"k":[0.541176470588,0.552941176471,0.968627510819,1]},"o":{"a":0,"k":100},"r":1,"bm":0,"nm":"Fill 1","hd":false},{"ty":"tr","p":{"a":0,"k":[-629.25,112.25]},"a":{"a":0,"k":[0,0]},"s":{"a":0,"k":[100,100]},"r":{"a":0,"k":0},"o":{"a":0,"k":100},"sk":{"a":0,"k":0},"sa":{"a":0,"k":0},"nm":"Transform"}],"nm":"Rectangle 1","bm":0,"hd":false}],"ip":0,"op":775,"st":0,"ct":1,"bm":0},{"ddd":0,"ind":5,"ty":4,"nm":"17","sr":1,"ks":{"o":{"a":0,"k":50},"r":{"a":0,"k":0},"p":{"a":0,"k":[1483,823.75,0]},"a":{"a":0,"k":[-629.25,162.8,0]},"s":{"a":1,"k":[{"i":{"x":[0.667,0.667,0.667],"y":[0.93,2.024,1]},"o":{"x":[0.333,0.333,0.333],"y":[0,0,0]},"t":100,"s":[100,100,100]},{"i":{"x":[0.651,0.49,0.667],"y":[1,1,1]},"o":{"x":[0.341,0.548,0.333],"y":[0.143,0.164,0]},"t":105,"s":[100,105,100]},{"i":{"x":[0.667,0.667,0.667],"y":[1,1,1]},"o":{"x":[0.167,0.167,0.167],"y":[0,0,0]},"t":115,"s":[100,2,100]},{"i":{"x":[0.311,0.301,0.667],"y":[1,1,1]},"o":{"x":[0.333,0.333,0.333],"y":[0,0,0]},"t":230,"s":[100,2,100]},{"t":248,"s":[100,100,100]}]}},"ao":0,"shapes":[{"ty":"gr","it":[{"ty":"rc","d":1,"s":{"a":0,"k":[64,101.053]},"p":{"a":0,"k":[0,0]},"r":{"a":0,"k":0},"nm":"Rectangle Path 1","hd":false},{"ty":"st","c":{"a":0,"k":[0.231372563979,0.211764720842,0.423529441684,1]},"o":{"a":0,"k":100},"w":{"a":0,"k":0},"lc":1,"lj":1,"ml":4,"bm":0,"nm":"Stroke 1","hd":false},{"ty":"fl","c":{"a":0,"k":[0.541176470588,0.552941176471,0.968627510819,1]},"o":{"a":0,"k":100},"r":1,"bm":0,"nm":"Fill 1","hd":false},{"ty":"tr","p":{"a":0,"k":[-629.25,112.25]},"a":{"a":0,"k":[0,0]},"s":{"a":0,"k":[100,100]},"r":{"a":0,"k":0},"o":{"a":0,"k":100},"sk":{"a":0,"k":0},"sa":{"a":0,"k":0},"nm":"Transform"}],"nm":"Rectangle 1","bm":0,"hd":false}],"ip":0,"op":775,"st":0,"ct":1,"bm":0},{"ddd":0,"ind":6,"ty":4,"nm":"16","sr":1,"ks":{"o":{"a":0,"k":50},"r":{"a":0,"k":0},"p":{"a":0,"k":[1413,823.75,0]},"a":{"a":0,"k":[-629.25,162.8,0]},"s":{"a":1,"k":[{"i":{"x":[0.667,0.667,0.667],"y":[0.93,2.024,1]},"o":{"x":[0.333,0.333,0.333],"y":[0,0,0]},"t":102,"s":[100,100,100]},{"i":{"x":[0.651,0.49,0.667],"y":[1,1,1]},"o":{"x":[0.341,0.548,0.333],"y":[0.143,0.164,0]},"t":107,"s":[100,105,100]},{"i":{"x":[0.667,0.667,0.667],"y":[1,1,1]},"o":{"x":[0.167,0.167,0.167],"y":[0,0,0]},"t":117,"s":[100,2,100]},{"i":{"x":[0.311,0.301,0.667],"y":[1,1,1]},"o":{"x":[0.333,0.333,0.333],"y":[0,0,0]},"t":230,"s":[100,2,100]},{"t":248,"s":[100,100,100]}]}},"ao":0,"shapes":[{"ty":"gr","it":[{"ty":"rc","d":1,"s":{"a":0,"k":[64,101.053]},"p":{"a":0,"k":[0,0]},"r":{"a":0,"k":0},"nm":"Rectangle Path 1","hd":false},{"ty":"st","c":{"a":0,"k":[0.231372563979,0.211764720842,0.423529441684,1]},"o":{"a":0,"k":100},"w":{"a":0,"k":0},"lc":1,"lj":1,"ml":4,"bm":0,"nm":"Stroke 1","hd":false},{"ty":"fl","c":{"a":0,"k":[0.541176470588,0.552941176471,0.968627510819,1]},"o":{"a":0,"k":100},"r":1,"bm":0,"nm":"Fill 1","hd":false},{"ty":"tr","p":{"a":0,"k":[-629.25,112.25]},"a":{"a":0,"k":[0,0]},"s":{"a":0,"k":[100,100]},"r":{"a":0,"k":0},"o":{"a":0,"k":100},"sk":{"a":0,"k":0},"sa":{"a":0,"k":0},"nm":"Transform"}],"nm":"Rectangle 1","bm":0,"hd":false}],"ip":0,"op":775,"st":0,"ct":1,"bm":0},{"ddd":0,"ind":7,"ty":4,"nm":"15","sr":1,"ks":{"o":{"a":0,"k":50},"r":{"a":0,"k":0},"p":{"a":0,"k":[1343,823.75,0]},"a":{"a":0,"k":[-629.25,162.8,0]},"s":{"a":1,"k":[{"i":{"x":[0.667,0.667,0.667],"y":[0.93,2.024,1]},"o":{"x":[0.333,0.333,0.333],"y":[0,0,0]},"t":104,"s":[100,100,100]},{"i":{"x":[0.651,0.49,0.667],"y":[1,1,1]},"o":{"x":[0.341,0.548,0.333],"y":[0.143,0.168,0]},"t":109,"s":[100,105,100]},{"i":{"x":[0.667,0.667,0.667],"y":[1,1,1]},"o":{"x":[0.167,0.167,0.167],"y":[0,0,0]},"t":119,"s":[100,5,100]},{"i":{"x":[0.311,0.301,0.667],"y":[1,1,1]},"o":{"x":[0.333,0.333,0.333],"y":[0,0,0]},"t":230,"s":[100,5,100]},{"t":248,"s":[100,100,100]}]}},"ao":0,"shapes":[{"ty":"gr","it":[{"ty":"rc","d":1,"s":{"a":0,"k":[64,101.053]},"p":{"a":0,"k":[0,0]},"r":{"a":0,"k":0},"nm":"Rectangle Path 1","hd":false},{"ty":"st","c":{"a":0,"k":[0.231372563979,0.211764720842,0.423529441684,1]},"o":{"a":0,"k":100},"w":{"a":0,"k":0},"lc":1,"lj":1,"ml":4,"bm":0,"nm":"Stroke 1","hd":false},{"ty":"fl","c":{"a":0,"k":[0.541176470588,0.552941176471,0.968627510819,1]},"o":{"a":0,"k":100},"r":1,"bm":0,"nm":"Fill 1","hd":false},{"ty":"tr","p":{"a":0,"k":[-629.25,112.25]},"a":{"a":0,"k":[0,0]},"s":{"a":0,"k":[100,100]},"r":{"a":0,"k":0},"o":{"a":0,"k":100},"sk":{"a":0,"k":0},"sa":{"a":0,"k":0},"nm":"Transform"}],"nm":"Rectangle 1","bm":0,"hd":false}],"ip":0,"op":775,"st":0,"ct":1,"bm":0},{"ddd":0,"ind":8,"ty":4,"nm":"14","sr":1,"ks":{"o":{"a":0,"k":50},"r":{"a":0,"k":0},"p":{"a":0,"k":[1273,823.75,0]},"a":{"a":0,"k":[-629.25,162.8,0]},"s":{"a":1,"k":[{"i":{"x":[0.667,0.667,0.667],"y":[0.93,2.024,1]},"o":{"x":[0.333,0.333,0.333],"y":[0,0,0]},"t":106,"s":[100,100,100]},{"i":{"x":[0.651,0.49,0.667],"y":[1,1,1]},"o":{"x":[0.341,0.548,0.333],"y":[0.143,0.187,0]},"t":111,"s":[100,105,100]},{"i":{"x":[0.667,0.667,0.667],"y":[1,1,1]},"o":{"x":[0.167,0.167,0.167],"y":[0,0,0]},"t":121,"s":[100,15,100]},{"i":{"x":[0.311,0.301,0.667],"y":[1,1,1]},"o":{"x":[0.333,0.333,0.333],"y":[0,0,0]},"t":230,"s":[100,15,100]},{"t":248,"s":[100,100,100]}]}},"ao":0,"shapes":[{"ty":"gr","it":[{"ty":"rc","d":1,"s":{"a":0,"k":[64,101.053]},"p":{"a":0,"k":[0,0]},"r":{"a":0,"k":0},"nm":"Rectangle Path 1","hd":false},{"ty":"st","c":{"a":0,"k":[0.231372563979,0.211764720842,0.423529441684,1]},"o":{"a":0,"k":100},"w":{"a":0,"k":0},"lc":1,"lj":1,"ml":4,"bm":0,"nm":"Stroke 1","hd":false},{"ty":"fl","c":{"a":0,"k":[0.541176470588,0.552941176471,0.968627510819,1]},"o":{"a":0,"k":100},"r":1,"bm":0,"nm":"Fill 1","hd":false},{"ty":"tr","p":{"a":0,"k":[-629.25,112.25]},"a":{"a":0,"k":[0,0]},"s":{"a":0,"k":[100,100]},"r":{"a":0,"k":0},"o":{"a":0,"k":100},"sk":{"a":0,"k":0},"sa":{"a":0,"k":0},"nm":"Transform"}],"nm":"Rectangle 1","bm":0,"hd":false}],"ip":0,"op":775,"st":0,"ct":1,"bm":0},{"ddd":0,"ind":9,"ty":4,"nm":"13","sr":1,"ks":{"o":{"a":0,"k":50},"r":{"a":0,"k":0},"p":{"a":0,"k":[1203,823.75,0]},"a":{"a":0,"k":[-629.25,162.8,0]},"s":{"a":1,"k":[{"i":{"x":[0.667,0.667,0.667],"y":[0.93,2.024,1]},"o":{"x":[0.333,0.333,0.333],"y":[0,0,0]},"t":108,"s":[100,100,100]},{"i":{"x":[0.651,0.49,0.667],"y":[1,1,1]},"o":{"x":[0.341,0.548,0.333],"y":[0.143,0.312,0]},"t":113,"s":[100,105,100]},{"i":{"x":[0.667,0.667,0.667],"y":[1,1,1]},"o":{"x":[0.167,0.167,0.167],"y":[0,0,0]},"t":123,"s":[100,51,100]},{"i":{"x":[0.311,0.301,0.667],"y":[1,1,1]},"o":{"x":[0.333,0.333,0.333],"y":[0,0,0]},"t":230,"s":[100,51,100]},{"t":248,"s":[100,100,100]}]}},"ao":0,"shapes":[{"ty":"gr","it":[{"ty":"rc","d":1,"s":{"a":0,"k":[64,101.053]},"p":{"a":0,"k":[0,0]},"r":{"a":0,"k":0},"nm":"Rectangle Path 1","hd":false},{"ty":"st","c":{"a":0,"k":[0.231372563979,0.211764720842,0.423529441684,1]},"o":{"a":0,"k":100},"w":{"a":0,"k":0},"lc":1,"lj":1,"ml":4,"bm":0,"nm":"Stroke 1","hd":false},{"ty":"fl","c":{"a":0,"k":[0.541176470588,0.552941176471,0.968627510819,1]},"o":{"a":0,"k":100},"r":1,"bm":0,"nm":"Fill 1","hd":false},{"ty":"tr","p":{"a":0,"k":[-629.25,112.25]},"a":{"a":0,"k":[0,0]},"s":{"a":0,"k":[100,100]},"r":{"a":0,"k":0},"o":{"a":0,"k":100},"sk":{"a":0,"k":0},"sa":{"a":0,"k":0},"nm":"Transform"}],"nm":"Rectangle 1","bm":0,"hd":false}],"ip":0,"op":775,"st":0,"ct":1,"bm":0},{"ddd":0,"ind":10,"ty":4,"nm":"12","sr":1,"ks":{"o":{"a":1,"k":[{"i":{"x":[0.833],"y":[0.833]},"o":{"x":[0.167],"y":[0.167]},"t":37,"s":[50]},{"i":{"x":[0.833],"y":[0.833]},"o":{"x":[0.167],"y":[0.167]},"t":39,"s":[100]},{"i":{"x":[0.833],"y":[0.833]},"o":{"x":[0.167],"y":[0.167]},"t":82,"s":[100]},{"t":87,"s":[50]}]},"r":{"a":0,"k":0},"p":{"a":0,"k":[1133,823.75,0]},"a":{"a":0,"k":[-629.25,162.8,0]},"s":{"a":1,"k":[{"i":{"x":[0.651,0.209,0.667],"y":[1,0.979,1]},"o":{"x":[0.333,0.333,0.333],"y":[0,0,0]},"t":110,"s":[100,100,100]},{"i":{"x":[0.667,0.667,0.667],"y":[1,1,1]},"o":{"x":[0.167,0.167,0.167],"y":[0,0,0]},"t":134,"s":[100,138,100]},{"i":{"x":[0.311,0.301,0.667],"y":[1,1,1]},"o":{"x":[0.333,0.333,0.333],"y":[0,0,0]},"t":230,"s":[100,138,100]},{"t":248,"s":[100,100,100]}]}},"ao":0,"shapes":[{"ty":"gr","it":[{"ty":"rc","d":1,"s":{"a":0,"k":[64,101.053]},"p":{"a":0,"k":[0,0]},"r":{"a":0,"k":0},"nm":"Rectangle Path 1","hd":false},{"ty":"st","c":{"a":0,"k":[0.231372563979,0.211764720842,0.423529441684,1]},"o":{"a":0,"k":100},"w":{"a":0,"k":0},"lc":1,"lj":1,"ml":4,"bm":0,"nm":"Stroke 1","hd":false},{"ty":"gf","o":{"a":0,"k":100},"r":1,"bm":0,"g":{"p":5,"k":{"a":0,"k":[0.005,0.584,0.596,0.969,0.251,0.665,0.674,0.965,0.497,0.746,0.753,0.961,0.727,0.665,0.674,0.965,0.957,0.584,0.596,0.969]}},"s":{"a":1,"k":[{"i":{"x":0.667,"y":1},"o":{"x":0.333,"y":0},"t":36,"s":[2,87.932],"to":[0,0],"ti":[0,0]},{"t":49.479,"s":[2,-273.902],"h":1},{"i":{"x":0.667,"y":1},"o":{"x":0.333,"y":0},"t":75,"s":[2,87.932],"to":[0,0],"ti":[0,0]},{"t":89.7626953125,"s":[2,-273.902],"h":1}]},"e":{"a":1,"k":[{"i":{"x":0.667,"y":1},"o":{"x":0.333,"y":0},"t":42.127,"s":[2,275.408],"to":[0,0],"ti":[0,0]},{"t":57,"s":[2,-73.348],"h":1},{"i":{"x":0.833,"y":0.833},"o":{"x":0.333,"y":0.333},"t":75,"s":[2,275.408],"to":[0,0],"ti":[0,0]},{"i":{"x":0.667,"y":1},"o":{"x":0.333,"y":0},"t":81.71,"s":[2,275.408],"to":[0,0],"ti":[0,0]},{"t":98,"s":[2,-73.348],"h":1}]},"t":1,"nm":"Gradient Fill 1","hd":false},{"ty":"fl","c":{"a":0,"k":[0.541176470588,0.552941176471,0.968627510819,1]},"o":{"a":0,"k":100},"r":1,"bm":0,"nm":"Fill 1","hd":false},{"ty":"tr","p":{"a":0,"k":[-629.25,112.25]},"a":{"a":0,"k":[0,0]},"s":{"a":0,"k":[100,100]},"r":{"a":0,"k":0},"o":{"a":0,"k":100},"sk":{"a":0,"k":0},"sa":{"a":0,"k":0},"nm":"Transform"}],"nm":"Rectangle 1","bm":0,"hd":false}],"ip":0,"op":775,"st":0,"ct":1,"bm":0},{"ddd":0,"ind":11,"ty":4,"nm":"11","sr":1,"ks":{"o":{"a":1,"k":[{"i":{"x":[0.833],"y":[0.833]},"o":{"x":[0.167],"y":[0.167]},"t":26,"s":[50]},{"i":{"x":[0.833],"y":[0.833]},"o":{"x":[0.167],"y":[0.167]},"t":28,"s":[100]},{"i":{"x":[0.833],"y":[0.833]},"o":{"x":[0.167],"y":[0.167]},"t":36,"s":[100]},{"i":{"x":[0.833],"y":[0.833]},"o":{"x":[0.167],"y":[0.167]},"t":41,"s":[50]},{"i":{"x":[0.833],"y":[0.833]},"o":{"x":[0.167],"y":[0.167]},"t":82,"s":[50]},{"i":{"x":[0.833],"y":[0.833]},"o":{"x":[0.167],"y":[0.167]},"t":84,"s":[100]},{"i":{"x":[0.833],"y":[0.833]},"o":{"x":[0.167],"y":[0.167]},"t":95,"s":[100]},{"t":100,"s":[50]}]},"r":{"a":0,"k":0},"p":{"a":0,"k":[1063,823.75,0]},"a":{"a":0,"k":[-629.25,162.8,0]},"s":{"a":1,"k":[{"i":{"x":[0.651,0.209,0.667],"y":[1,0.995,1]},"o":{"x":[0.333,0.333,0.333],"y":[0,0,0]},"t":112,"s":[100,100,100]},{"i":{"x":[0.833,0.833,0.833],"y":[1,1,1]},"o":{"x":[0.167,0.167,0.167],"y":[0,0,0]},"t":136,"s":[100,265,100]},{"i":{"x":[0.833,0.833,0.833],"y":[1,1,1]},"o":{"x":[0.167,0.167,0.167],"y":[0,0,0]},"t":168,"s":[100,229,100]},{"i":{"x":[0.667,0.667,0.667],"y":[1,1,1]},"o":{"x":[0.167,0.167,0.167],"y":[0,0,0]},"t":198,"s":[100,229,100]},{"i":{"x":[0.311,0.301,0.667],"y":[1,1,1]},"o":{"x":[0.333,0.333,0.333],"y":[0,0,0]},"t":230,"s":[100,265,100]},{"i":{"x":[0.667,0.667,0.667],"y":[1,1,1]},"o":{"x":[0.333,0.333,0.333],"y":[0,0,0]},"t":248,"s":[100,100,100]},{"i":{"x":[0.833,0.833,0.833],"y":[1,1,1]},"o":{"x":[0.167,0.167,0.167],"y":[0,0,0]},"t":380,"s":[100,284,100]},{"t":418,"s":[100,265,100]}]}},"ao":0,"shapes":[{"ty":"gr","it":[{"ty":"rc","d":1,"s":{"a":0,"k":[64,101.053]},"p":{"a":0,"k":[0,0]},"r":{"a":0,"k":0},"nm":"Rectangle Path 1","hd":false},{"ty":"st","c":{"a":0,"k":[0.231372563979,0.211764720842,0.423529441684,1]},"o":{"a":0,"k":100},"w":{"a":0,"k":0},"lc":1,"lj":1,"ml":4,"bm":0,"nm":"Stroke 1","hd":false},{"ty":"gf","o":{"a":0,"k":100},"r":1,"bm":0,"g":{"p":5,"k":{"a":0,"k":[0.005,0.584,0.596,0.969,0.251,0.665,0.674,0.965,0.497,0.746,0.753,0.961,0.727,0.665,0.674,0.965,0.957,0.584,0.596,0.969]}},"s":{"a":1,"k":[{"i":{"x":0.667,"y":1},"o":{"x":0.333,"y":0},"t":22,"s":[2,87.932],"to":[0,0],"ti":[0,0]},{"t":39.331,"s":[2,-273.902],"h":1},{"i":{"x":0.667,"y":1},"o":{"x":0.333,"y":0},"t":82,"s":[2,87.932],"to":[0,0],"ti":[0,0]},{"t":97.4052734375,"s":[2,-273.902],"h":1}]},"e":{"a":1,"k":[{"i":{"x":0.667,"y":1},"o":{"x":0.333,"y":0},"t":29.878,"s":[2,275.408],"to":[0,0],"ti":[0,0]},{"t":49,"s":[2,-73.348],"h":1},{"i":{"x":0.833,"y":0.833},"o":{"x":0.333,"y":0.333},"t":82,"s":[2,275.408],"to":[0,0],"ti":[0,0]},{"i":{"x":0.667,"y":1},"o":{"x":0.333,"y":0},"t":89.002,"s":[2,275.408],"to":[0,0],"ti":[0,0]},{"t":110,"s":[2,-73.348],"h":1}]},"t":1,"nm":"Gradient Fill 1","hd":false},{"ty":"fl","c":{"a":0,"k":[0.541176470588,0.552941176471,0.968627510819,1]},"o":{"a":0,"k":100},"r":1,"bm":0,"nm":"Fill 1","hd":false},{"ty":"tr","p":{"a":0,"k":[-629.25,112.25]},"a":{"a":0,"k":[0,0]},"s":{"a":0,"k":[100,100]},"r":{"a":0,"k":0},"o":{"a":0,"k":100},"sk":{"a":0,"k":0},"sa":{"a":0,"k":0},"nm":"Transform"}],"nm":"Rectangle 1","bm":0,"hd":false}],"ip":0,"op":775,"st":0,"ct":1,"bm":0},{"ddd":0,"ind":12,"ty":4,"nm":"10","sr":1,"ks":{"o":{"a":1,"k":[{"i":{"x":[0.833],"y":[0.833]},"o":{"x":[0.167],"y":[0.167]},"t":8,"s":[50]},{"i":{"x":[0.833],"y":[0.833]},"o":{"x":[0.167],"y":[0.167]},"t":10,"s":[100]},{"i":{"x":[0.833],"y":[0.833]},"o":{"x":[0.167],"y":[0.167]},"t":25,"s":[100]},{"i":{"x":[0.833],"y":[0.833]},"o":{"x":[0.167],"y":[0.167]},"t":30,"s":[50]},{"i":{"x":[0.833],"y":[0.833]},"o":{"x":[0.167],"y":[0.167]},"t":97,"s":[50]},{"i":{"x":[0.833],"y":[0.833]},"o":{"x":[0.167],"y":[0.167]},"t":99,"s":[100]},{"i":{"x":[0.833],"y":[0.833]},"o":{"x":[0.167],"y":[0.167]},"t":119,"s":[100]},{"i":{"x":[0.833],"y":[0.833]},"o":{"x":[0.167],"y":[0.167]},"t":124,"s":[50]},{"i":{"x":[0.833],"y":[0.833]},"o":{"x":[0.167],"y":[0.167]},"t":311,"s":[50]},{"i":{"x":[0.833],"y":[0.833]},"o":{"x":[0.167],"y":[0.167]},"t":313,"s":[100]},{"i":{"x":[0.833],"y":[0.833]},"o":{"x":[0.167],"y":[0.167]},"t":390,"s":[100]},{"t":395,"s":[50]}]},"r":{"a":0,"k":0},"p":{"a":0,"k":[993,823.75,0]},"a":{"a":0,"k":[-629.25,162.8,0]},"s":{"a":1,"k":[{"i":{"x":[0.651,0.209,0.667],"y":[1,0.997,1]},"o":{"x":[0.333,0.333,0.333],"y":[0,0,0]},"t":114,"s":[100,100,100]},{"i":{"x":[0.833,0.833,0.833],"y":[1,1,1]},"o":{"x":[0.167,0.167,0.167],"y":[0,0,0]},"t":138,"s":[100,357,100]},{"i":{"x":[0.667,0.667,0.667],"y":[1,1,1]},"o":{"x":[0.167,0.167,0.167],"y":[0,0,0]},"t":185,"s":[100,284,100]},{"i":{"x":[0.311,0.301,0.667],"y":[1,1,1]},"o":{"x":[0.333,0.333,0.333],"y":[0,0,0]},"t":230,"s":[100,357,100]},{"i":{"x":[0.667,0.667,0.667],"y":[1,1,1]},"o":{"x":[0.333,0.333,0.333],"y":[0,0,0]},"t":248,"s":[100,100,100]},{"i":{"x":[0.833,0.833,0.833],"y":[1,1,1]},"o":{"x":[0.167,0.167,0.167],"y":[0,0,0]},"t":380,"s":[100,392,100]},{"t":418,"s":[100,357,100]}]}},"ao":0,"shapes":[{"ty":"gr","it":[{"ty":"rc","d":1,"s":{"a":0,"k":[64,101.053]},"p":{"a":0,"k":[0,0]},"r":{"a":0,"k":0},"nm":"Rectangle Path 1","hd":false},{"ty":"st","c":{"a":0,"k":[0.231372563979,0.211764720842,0.423529441684,1]},"o":{"a":0,"k":100},"w":{"a":0,"k":0},"lc":1,"lj":1,"ml":4,"bm":0,"nm":"Stroke 1","hd":false},{"ty":"gf","o":{"a":0,"k":100},"r":1,"bm":0,"g":{"p":5,"k":{"a":0,"k":[0.005,0.584,0.596,0.969,0.251,0.682,0.691,0.965,0.497,0.78,0.785,0.961,0.727,0.682,0.691,0.965,0.957,0.584,0.596,0.969]}},"s":{"a":1,"k":[{"i":{"x":0.667,"y":1},"o":{"x":0.333,"y":0},"t":7,"s":[2,87.932],"to":[0,0],"ti":[0,0]},{"t":18,"s":[2,-273.902],"h":1},{"i":{"x":0.667,"y":1},"o":{"x":0.333,"y":0},"t":95,"s":[2,87.932],"to":[0,0],"ti":[0,0]},{"t":106,"s":[2,-273.902],"h":1},{"i":{"x":0.667,"y":1},"o":{"x":0.333,"y":0},"t":315,"s":[2,87.932],"to":[0,0],"ti":[0,0]},{"t":326,"s":[2,-273.902],"h":1},{"i":{"x":0.667,"y":1},"o":{"x":0.333,"y":0},"t":357,"s":[2,87.932],"to":[0,0],"ti":[0,0]},{"t":368,"s":[2,-273.902],"h":1}]},"e":{"a":1,"k":[{"i":{"x":0.667,"y":1},"o":{"x":0.333,"y":0},"t":12,"s":[2,275.408],"to":[0,0],"ti":[0,0]},{"t":30,"s":[2,-73.348],"h":1},{"i":{"x":0.667,"y":0.667},"o":{"x":0.333,"y":0.333},"t":95,"s":[2,275.408],"to":[0,0],"ti":[0,0]},{"i":{"x":0.667,"y":1},"o":{"x":0.333,"y":0},"t":100,"s":[2,275.408],"to":[0,0],"ti":[0,0]},{"t":118,"s":[2,-73.348],"h":1},{"i":{"x":0.667,"y":0.667},"o":{"x":0.333,"y":0.333},"t":315,"s":[2,275.408],"to":[0,0],"ti":[0,0]},{"i":{"x":0.667,"y":1},"o":{"x":0.333,"y":0},"t":320,"s":[2,275.408],"to":[0,0],"ti":[0,0]},{"t":338,"s":[2,-73.348],"h":1},{"i":{"x":0.667,"y":0.667},"o":{"x":0.333,"y":0.333},"t":357,"s":[2,275.408],"to":[0,0],"ti":[0,0]},{"i":{"x":0.667,"y":1},"o":{"x":0.333,"y":0},"t":362,"s":[2,275.408],"to":[0,0],"ti":[0,0]},{"t":380,"s":[2,-73.348],"h":1}]},"t":1,"nm":"Gradient Fill 1","hd":false},{"ty":"fl","c":{"a":0,"k":[0.58431372549,0.596078431373,0.968627510819,1]},"o":{"a":0,"k":100},"r":1,"bm":0,"nm":"Fill 1","hd":false},{"ty":"tr","p":{"a":0,"k":[-629.25,112.25]},"a":{"a":0,"k":[0,0]},"s":{"a":0,"k":[100,100]},"r":{"a":0,"k":0},"o":{"a":0,"k":100},"sk":{"a":0,"k":0},"sa":{"a":0,"k":0},"nm":"Transform"}],"nm":"Rectangle 1","bm":0,"hd":false},{"ty":"gr","it":[{"ty":"tr","p":{"a":0,"k":[0,0]},"a":{"a":0,"k":[0,0]},"s":{"a":0,"k":[100,100]},"r":{"a":0,"k":0},"o":{"a":0,"k":100},"sk":{"a":0,"k":0},"sa":{"a":0,"k":0},"nm":"Transform"}],"nm":"Group 1","bm":0,"hd":false}],"ip":0,"op":775,"st":0,"ct":1,"bm":0},{"ddd":0,"ind":14,"ty":4,"nm":"19","sr":1,"ks":{"o":{"a":1,"k":[{"i":{"x":[0.833],"y":[0.833]},"o":{"x":[0.167],"y":[0.167]},"t":7,"s":[100]},{"i":{"x":[0.833],"y":[0.833]},"o":{"x":[0.167],"y":[0.167]},"t":13,"s":[50]},{"i":{"x":[0.833],"y":[0.833]},"o":{"x":[0.167],"y":[0.167]},"t":124,"s":[50]},{"i":{"x":[0.833],"y":[0.833]},"o":{"x":[0.167],"y":[0.167]},"t":126,"s":[100]},{"i":{"x":[0.833],"y":[0.833]},"o":{"x":[0.167],"y":[0.167]},"t":157,"s":[100]},{"i":{"x":[0.833],"y":[0.833]},"o":{"x":[0.167],"y":[0.167]},"t":162,"s":[50]},{"i":{"x":[0.833],"y":[0.833]},"o":{"x":[0.167],"y":[0.167]},"t":200,"s":[50]},{"i":{"x":[0.833],"y":[0.833]},"o":{"x":[0.167],"y":[0.167]},"t":202,"s":[100]},{"i":{"x":[0.833],"y":[0.833]},"o":{"x":[0.167],"y":[0.167]},"t":311,"s":[100]},{"i":{"x":[0.833],"y":[0.833]},"o":{"x":[0.167],"y":[0.167]},"t":316,"s":[50]},{"i":{"x":[0.833],"y":[0.833]},"o":{"x":[0.167],"y":[0.167]},"t":390,"s":[50]},{"t":392,"s":[100]}]},"r":{"a":0,"k":0},"p":{"a":0,"k":[923,823.75,0]},"a":{"a":0,"k":[-629.25,162.8,0]},"s":{"a":1,"k":[{"i":{"x":[0.651,0.209,0.667],"y":[1,0.997,1]},"o":{"x":[0.333,0.333,0.333],"y":[0,0,0]},"t":115,"s":[100,100,100]},{"i":{"x":[0.606,0.606,0.606],"y":[1,1,1]},"o":{"x":[0.167,0.167,0.167],"y":[0,0,0]},"t":139,"s":[100,416,100]},{"i":{"x":[0.625,0.625,0.625],"y":[1,1,1]},"o":{"x":[0.286,0.286,0.286],"y":[0,0,0]},"t":161,"s":[100,416,100]},{"i":{"x":[0.698,0.698,0.698],"y":[1,1,1]},"o":{"x":[0.291,0.291,0.291],"y":[0,0,0]},"t":189,"s":[100,356,100]},{"i":{"x":[0.311,0.301,0.667],"y":[1,1,1]},"o":{"x":[0.333,0.333,0.333],"y":[0,0,0]},"t":230,"s":[100,416,100]},{"i":{"x":[0.667,0.667,0.667],"y":[1,1,1]},"o":{"x":[0.333,0.333,0.333],"y":[0,0,0]},"t":248,"s":[100,100,100]},{"i":{"x":[0.833,0.833,0.833],"y":[1,1,1]},"o":{"x":[0.167,0.167,0.167],"y":[0,0,0]},"t":380,"s":[100,407,100]},{"t":418,"s":[100,416,100]}]}},"ao":0,"shapes":[{"ty":"gr","it":[{"ty":"rc","d":1,"s":{"a":0,"k":[64,101.053]},"p":{"a":0,"k":[0,0]},"r":{"a":0,"k":0},"nm":"Rectangle Path 1","hd":false},{"ty":"st","c":{"a":0,"k":[0.231372563979,0.211764720842,0.423529441684,1]},"o":{"a":0,"k":100},"w":{"a":0,"k":0},"lc":1,"lj":1,"ml":4,"bm":0,"nm":"Stroke 1","hd":false},{"ty":"gf","o":{"a":0,"k":100},"r":1,"bm":0,"g":{"p":5,"k":{"a":0,"k":[0.005,0.584,0.596,0.969,0.251,0.652,0.661,0.957,0.497,0.719,0.726,0.945,0.727,0.652,0.661,0.957,0.957,0.584,0.596,0.969]}},"s":{"a":1,"k":[{"i":{"x":0.667,"y":1},"o":{"x":0.333,"y":0},"t":125,"s":[2,87.932],"to":[0,0],"ti":[0,0]},{"t":132.174,"s":[2,-273.902],"h":1},{"i":{"x":0.667,"y":1},"o":{"x":0.333,"y":0},"t":203,"s":[2,87.932],"to":[0,0],"ti":[0,0]},{"t":214,"s":[2,-273.902],"h":1},{"i":{"x":0.667,"y":1},"o":{"x":0.333,"y":0},"t":409,"s":[2,87.932],"to":[0,0],"ti":[0,0]},{"t":420,"s":[2,-273.902],"h":1}]},"e":{"a":1,"k":[{"i":{"x":0.667,"y":1},"o":{"x":0.333,"y":0},"t":129,"s":[2,275.408],"to":[0,0],"ti":[0,0]},{"t":140.739,"s":[2,-73.348],"h":1},{"i":{"x":0.833,"y":0.833},"o":{"x":0.333,"y":0.333},"t":203,"s":[2,275.408],"to":[0,0],"ti":[0,0]},{"i":{"x":0.667,"y":1},"o":{"x":0.333,"y":0},"t":209.739,"s":[2,275.408],"to":[0,0],"ti":[0,0]},{"t":227.739,"s":[2,-73.348],"h":1},{"i":{"x":0.833,"y":0.833},"o":{"x":0.333,"y":0.333},"t":409.739,"s":[2,275.408],"to":[0,0],"ti":[0,0]},{"i":{"x":0.667,"y":1},"o":{"x":0.333,"y":0},"t":414.739,"s":[2,275.408],"to":[0,0],"ti":[0,0]},{"t":432.7392578125,"s":[2,-73.348],"h":1}]},"t":1,"nm":"Gradient Fill 1","hd":false},{"ty":"fl","c":{"a":0,"k":[0.541176470588,0.552941176471,0.968627510819,1]},"o":{"a":0,"k":100},"r":1,"bm":0,"nm":"Fill 1","hd":false},{"ty":"tr","p":{"a":0,"k":[-629.25,112.25]},"a":{"a":0,"k":[0,0]},"s":{"a":0,"k":[100,100]},"r":{"a":0,"k":0},"o":{"a":0,"k":100},"sk":{"a":0,"k":0},"sa":{"a":0,"k":0},"nm":"Transform"}],"nm":"Rectangle 1","bm":0,"hd":false}],"ip":0,"op":775,"st":0,"ct":1,"bm":0},{"ddd":0,"ind":15,"ty":4,"nm":"8","sr":1,"ks":{"o":{"a":1,"k":[{"i":{"x":[0.833],"y":[0.833]},"o":{"x":[0.167],"y":[0.167]},"t":158,"s":[50]},{"i":{"x":[0.833],"y":[0.833]},"o":{"x":[0.167],"y":[0.167]},"t":160,"s":[100]},{"i":{"x":[0.833],"y":[0.833]},"o":{"x":[0.167],"y":[0.167]},"t":200,"s":[100]},{"t":205,"s":[50]}]},"r":{"a":0,"k":0},"p":{"a":0,"k":[853,823.75,0]},"a":{"a":0,"k":[-629.25,162.8,0]},"s":{"a":1,"k":[{"i":{"x":[0.651,0.209,0.667],"y":[1,0.995,1]},"o":{"x":[0.333,0.333,0.333],"y":[0,0,0]},"t":113,"s":[100,100,100]},{"i":{"x":[0.57,0.57,0.57],"y":[1,1,1]},"o":{"x":[0.209,0.209,0.209],"y":[0,0,0]},"t":137,"s":[100,265,100]},{"i":{"x":[0.347,0.306,0.652],"y":[1,1,1]},"o":{"x":[0.314,0.314,0.314],"y":[0,0,0]},"t":159,"s":[100,265,100]},{"i":{"x":[0.652,0.652,0.652],"y":[1,1,1]},"o":{"x":[0.339,0.339,0.339],"y":[0,0,0]},"t":190,"s":[100,388,100]},{"i":{"x":[0.703,0.703,0.703],"y":[1,1,1]},"o":{"x":[0.461,0.533,0.339],"y":[0,0,0]},"t":203,"s":[100,327,100]},{"i":{"x":[0.311,0.301,0.667],"y":[1,1,1]},"o":{"x":[0.333,0.333,0.333],"y":[0,0,0]},"t":230,"s":[100,265,100]},{"t":248,"s":[100,100,100]}]}},"ao":0,"shapes":[{"ty":"gr","it":[{"ty":"rc","d":1,"s":{"a":0,"k":[64,101.053]},"p":{"a":0,"k":[0,0]},"r":{"a":0,"k":0},"nm":"Rectangle Path 1","hd":false},{"ty":"st","c":{"a":0,"k":[0.231372563979,0.211764720842,0.423529441684,1]},"o":{"a":0,"k":100},"w":{"a":0,"k":0},"lc":1,"lj":1,"ml":4,"bm":0,"nm":"Stroke 1","hd":false},{"ty":"gf","o":{"a":0,"k":100},"r":1,"bm":0,"g":{"p":5,"k":{"a":0,"k":[0.005,0.584,0.596,0.969,0.251,0.665,0.674,0.965,0.497,0.746,0.753,0.961,0.727,0.665,0.674,0.965,0.957,0.584,0.596,0.969]}},"s":{"a":1,"k":[{"i":{"x":0.667,"y":1},"o":{"x":0.333,"y":0},"t":163,"s":[2,87.932],"to":[0,0],"ti":[0,0]},{"t":172.5654296875,"s":[2,-273.902],"h":1}]},"e":{"a":1,"k":[{"i":{"x":0.667,"y":1},"o":{"x":0.333,"y":0},"t":167.348,"s":[2,275.408],"to":[0,0],"ti":[0,0]},{"t":183,"s":[2,-73.348],"h":1}]},"t":1,"nm":"Gradient Fill 1","hd":false},{"ty":"fl","c":{"a":0,"k":[0.541176470588,0.552941176471,0.968627510819,1]},"o":{"a":0,"k":100},"r":1,"bm":0,"nm":"Fill 1","hd":false},{"ty":"tr","p":{"a":0,"k":[-629.25,112.25]},"a":{"a":0,"k":[0,0]},"s":{"a":0,"k":[100,100]},"r":{"a":0,"k":0},"o":{"a":0,"k":100},"sk":{"a":0,"k":0},"sa":{"a":0,"k":0},"nm":"Transform"}],"nm":"Rectangle 1","bm":0,"hd":false}],"ip":0,"op":775,"st":0,"ct":1,"bm":0},{"ddd":0,"ind":16,"ty":4,"nm":"7","sr":1,"ks":{"o":{"a":0,"k":50},"r":{"a":0,"k":0},"p":{"a":0,"k":[783,823.75,0]},"a":{"a":0,"k":[-629.25,162.8,0]},"s":{"a":1,"k":[{"i":{"x":[0.651,0.209,0.667],"y":[1,0.978,1]},"o":{"x":[0.333,0.333,0.333],"y":[0,0,0]},"t":111,"s":[100,100,100]},{"i":{"x":[0.569,0.569,0.569],"y":[1,1,1]},"o":{"x":[0.201,0.201,0.201],"y":[0,0,0]},"t":135,"s":[100,136,100]},{"i":{"x":[0.658,0.658,0.658],"y":[1,1,1]},"o":{"x":[0.315,0.315,0.315],"y":[0,0,0]},"t":162,"s":[100,136,100]},{"i":{"x":[0.7,0.7,0.7],"y":[1,1,1]},"o":{"x":[0.351,0.351,0.351],"y":[0,0,0]},"t":189,"s":[100,312,100]},{"i":{"x":[0.311,0.301,0.667],"y":[1,1,1]},"o":{"x":[0.333,0.333,0.333],"y":[0,0,0]},"t":230,"s":[100,136,100]},{"t":248,"s":[100,100,100]}]}},"ao":0,"shapes":[{"ty":"gr","it":[{"ty":"rc","d":1,"s":{"a":0,"k":[64,101.053]},"p":{"a":0,"k":[0,0]},"r":{"a":0,"k":0},"nm":"Rectangle Path 1","hd":false},{"ty":"st","c":{"a":0,"k":[0.231372563979,0.211764720842,0.423529441684,1]},"o":{"a":0,"k":100},"w":{"a":0,"k":0},"lc":1,"lj":1,"ml":4,"bm":0,"nm":"Stroke 1","hd":false},{"ty":"fl","c":{"a":0,"k":[0.541176470588,0.552941176471,0.968627510819,1]},"o":{"a":0,"k":100},"r":1,"bm":0,"nm":"Fill 1","hd":false},{"ty":"tr","p":{"a":0,"k":[-629.25,112.25]},"a":{"a":0,"k":[0,0]},"s":{"a":0,"k":[100,100]},"r":{"a":0,"k":0},"o":{"a":0,"k":100},"sk":{"a":0,"k":0},"sa":{"a":0,"k":0},"nm":"Transform"}],"nm":"Rectangle 1","bm":0,"hd":false}],"ip":0,"op":775,"st":0,"ct":1,"bm":0},{"ddd":0,"ind":17,"ty":4,"nm":"6","sr":1,"ks":{"o":{"a":0,"k":50},"r":{"a":0,"k":0},"p":{"a":0,"k":[713,823.75,0]},"a":{"a":0,"k":[-629.25,162.8,0]},"s":{"a":1,"k":[{"i":{"x":[0.667,0.667,0.667],"y":[0.93,2.024,1]},"o":{"x":[0.333,0.333,0.333],"y":[0,0,0]},"t":108,"s":[100,100,100]},{"i":{"x":[0.651,0.49,0.667],"y":[1,1,1]},"o":{"x":[0.341,0.548,0.333],"y":[0.143,0.312,0]},"t":113,"s":[100,105,100]},{"i":{"x":[0.57,0.57,0.57],"y":[1,1,1]},"o":{"x":[0.194,0.194,0.194],"y":[0,0,0]},"t":123,"s":[100,51,100]},{"i":{"x":[0.66,0.66,0.66],"y":[1,1,1]},"o":{"x":[0.322,0.322,0.322],"y":[0,0,0]},"t":166,"s":[100,51,100]},{"i":{"x":[0.701,0.701,0.701],"y":[1,1,1]},"o":{"x":[0.349,0.349,0.349],"y":[0,0,0]},"t":188,"s":[100,166,100]},{"i":{"x":[0.311,0.301,0.667],"y":[1,1,1]},"o":{"x":[0.333,0.333,0.333],"y":[0,0,0]},"t":230,"s":[100,51,100]},{"t":248,"s":[100,100,100]}]}},"ao":0,"shapes":[{"ty":"gr","it":[{"ty":"rc","d":1,"s":{"a":0,"k":[64,101.053]},"p":{"a":0,"k":[0,0]},"r":{"a":0,"k":0},"nm":"Rectangle Path 1","hd":false},{"ty":"st","c":{"a":0,"k":[0.231372563979,0.211764720842,0.423529441684,1]},"o":{"a":0,"k":100},"w":{"a":0,"k":0},"lc":1,"lj":1,"ml":4,"bm":0,"nm":"Stroke 1","hd":false},{"ty":"fl","c":{"a":0,"k":[0.541176470588,0.552941176471,0.968627510819,1]},"o":{"a":0,"k":100},"r":1,"bm":0,"nm":"Fill 1","hd":false},{"ty":"tr","p":{"a":0,"k":[-629.25,112.25]},"a":{"a":0,"k":[0,0]},"s":{"a":0,"k":[100,100]},"r":{"a":0,"k":0},"o":{"a":0,"k":100},"sk":{"a":0,"k":0},"sa":{"a":0,"k":0},"nm":"Transform"}],"nm":"Rectangle 1","bm":0,"hd":false}],"ip":0,"op":775,"st":0,"ct":1,"bm":0},{"ddd":0,"ind":18,"ty":4,"nm":"5","sr":1,"ks":{"o":{"a":0,"k":50},"r":{"a":0,"k":0},"p":{"a":0,"k":[643,823.75,0]},"a":{"a":0,"k":[-629.25,162.8,0]},"s":{"a":1,"k":[{"i":{"x":[0.667,0.667,0.667],"y":[0.93,2.024,1]},"o":{"x":[0.333,0.333,0.333],"y":[0,0,0]},"t":106,"s":[100,100,100]},{"i":{"x":[0.651,0.49,0.667],"y":[1,1,1]},"o":{"x":[0.341,0.548,0.333],"y":[0.143,0.208,0]},"t":111,"s":[100,105,100]},{"i":{"x":[0.571,0.571,0.571],"y":[1,1,1]},"o":{"x":[0.192,0.192,0.192],"y":[0,0,0]},"t":121,"s":[100,24,100]},{"i":{"x":[0.662,0.662,0.662],"y":[1,1,1]},"o":{"x":[0.324,0.324,0.324],"y":[0,0,0]},"t":167,"s":[100,24,100]},{"i":{"x":[0.699,0.699,0.699],"y":[1,1,1]},"o":{"x":[0.351,0.351,0.351],"y":[0,0,0]},"t":191,"s":[100,75,100]},{"i":{"x":[0.311,0.301,0.667],"y":[1,1,1]},"o":{"x":[0.333,0.333,0.333],"y":[0,0,0]},"t":230,"s":[100,24,100]},{"t":248,"s":[100,100,100]}]}},"ao":0,"shapes":[{"ty":"gr","it":[{"ty":"rc","d":1,"s":{"a":0,"k":[64,101.053]},"p":{"a":0,"k":[0,0]},"r":{"a":0,"k":0},"nm":"Rectangle Path 1","hd":false},{"ty":"st","c":{"a":0,"k":[0.231372563979,0.211764720842,0.423529441684,1]},"o":{"a":0,"k":100},"w":{"a":0,"k":0},"lc":1,"lj":1,"ml":4,"bm":0,"nm":"Stroke 1","hd":false},{"ty":"fl","c":{"a":0,"k":[0.541176470588,0.552941176471,0.968627510819,1]},"o":{"a":0,"k":100},"r":1,"bm":0,"nm":"Fill 1","hd":false},{"ty":"tr","p":{"a":0,"k":[-629.25,112.25]},"a":{"a":0,"k":[0,0]},"s":{"a":0,"k":[100,100]},"r":{"a":0,"k":0},"o":{"a":0,"k":100},"sk":{"a":0,"k":0},"sa":{"a":0,"k":0},"nm":"Transform"}],"nm":"Rectangle 1","bm":0,"hd":false}],"ip":0,"op":775,"st":0,"ct":1,"bm":0},{"ddd":0,"ind":19,"ty":4,"nm":"4","sr":1,"ks":{"o":{"a":0,"k":50},"r":{"a":0,"k":0},"p":{"a":0,"k":[573,823.75,0]},"a":{"a":0,"k":[-629.25,162.8,0]},"s":{"a":1,"k":[{"i":{"x":[0.667,0.667,0.667],"y":[0.93,2.024,1]},"o":{"x":[0.333,0.333,0.333],"y":[0,0,0]},"t":104,"s":[100,100,100]},{"i":{"x":[0.651,0.49,0.667],"y":[1,1,1]},"o":{"x":[0.341,0.548,0.333],"y":[0.143,0.168,0]},"t":109,"s":[100,105,100]},{"i":{"x":[0.667,0.667,0.667],"y":[1,1,1]},"o":{"x":[0.167,0.167,0.167],"y":[0,0,0]},"t":119,"s":[100,5,100]},{"i":{"x":[0.311,0.301,0.667],"y":[1,1,1]},"o":{"x":[0.333,0.333,0.333],"y":[0,0,0]},"t":230,"s":[100,5,100]},{"t":248,"s":[100,100,100]}]}},"ao":0,"shapes":[{"ty":"gr","it":[{"ty":"rc","d":1,"s":{"a":0,"k":[64,101.053]},"p":{"a":0,"k":[0,0]},"r":{"a":0,"k":0},"nm":"Rectangle Path 1","hd":false},{"ty":"st","c":{"a":0,"k":[0.231372563979,0.211764720842,0.423529441684,1]},"o":{"a":0,"k":100},"w":{"a":0,"k":0},"lc":1,"lj":1,"ml":4,"bm":0,"nm":"Stroke 1","hd":false},{"ty":"fl","c":{"a":0,"k":[0.549019607843,0.541176470588,0.976470588235,1]},"o":{"a":0,"k":100},"r":1,"bm":0,"nm":"Fill 1","hd":false},{"ty":"tr","p":{"a":0,"k":[-629.25,112.25]},"a":{"a":0,"k":[0,0]},"s":{"a":0,"k":[100,100]},"r":{"a":0,"k":0},"o":{"a":0,"k":100},"sk":{"a":0,"k":0},"sa":{"a":0,"k":0},"nm":"Transform"}],"nm":"Rectangle 1","bm":0,"hd":false}],"ip":0,"op":775,"st":0,"ct":1,"bm":0},{"ddd":0,"ind":20,"ty":4,"nm":"3","sr":1,"ks":{"o":{"a":0,"k":50},"r":{"a":0,"k":0},"p":{"a":0,"k":[503,823.75,0]},"a":{"a":0,"k":[-629.25,162.8,0]},"s":{"a":1,"k":[{"i":{"x":[0.667,0.667,0.667],"y":[1.007,2.01,1]},"o":{"x":[0.333,0.333,0.333],"y":[0,0,0]},"t":102,"s":[100,100,100]},{"i":{"x":[0.473,0.473,0.667],"y":[1,1,1]},"o":{"x":[0.556,0.556,0.333],"y":[-0.023,0.169,0]},"t":107,"s":[100,105,100]},{"i":{"x":[0.667,0.667,0.667],"y":[1,1,1]},"o":{"x":[0.167,0.167,0.167],"y":[0,0,0]},"t":117,"s":[100,5,100]},{"i":{"x":[0.311,0.301,0.667],"y":[1,1,1]},"o":{"x":[0.333,0.333,0.333],"y":[0,0,0]},"t":230,"s":[100,5,100]},{"t":248,"s":[100,100,100]}]}},"ao":0,"shapes":[{"ty":"gr","it":[{"ty":"rc","d":1,"s":{"a":0,"k":[64,101.053]},"p":{"a":0,"k":[0,0]},"r":{"a":0,"k":0},"nm":"Rectangle Path 1","hd":false},{"ty":"st","c":{"a":0,"k":[0.231372563979,0.211764720842,0.423529441684,1]},"o":{"a":0,"k":100},"w":{"a":0,"k":0},"lc":1,"lj":1,"ml":4,"bm":0,"nm":"Stroke 1","hd":false},{"ty":"fl","c":{"a":0,"k":[0.549019607843,0.541176470588,0.976470588235,1]},"o":{"a":0,"k":100},"r":1,"bm":0,"nm":"Fill 1","hd":false},{"ty":"tr","p":{"a":0,"k":[-629.25,112.25]},"a":{"a":0,"k":[0,0]},"s":{"a":0,"k":[100,100]},"r":{"a":0,"k":0},"o":{"a":0,"k":100},"sk":{"a":0,"k":0},"sa":{"a":0,"k":0},"nm":"Transform"}],"nm":"Rectangle 1","bm":0,"hd":false}],"ip":0,"op":775,"st":0,"ct":1,"bm":0},{"ddd":0,"ind":21,"ty":4,"nm":"2","sr":1,"ks":{"o":{"a":0,"k":50},"r":{"a":0,"k":0},"p":{"a":0,"k":[433,823.75,0]},"a":{"a":0,"k":[-629.25,162.8,0]},"s":{"a":1,"k":[{"i":{"x":[0.667,0.667,0.667],"y":[1.007,2.01,1]},"o":{"x":[0.333,0.333,0.333],"y":[0,0,0]},"t":100,"s":[100,100,100]},{"i":{"x":[0.473,0.473,0.667],"y":[1,1,1]},"o":{"x":[0.556,0.556,0.333],"y":[-0.023,0.169,0]},"t":105,"s":[100,105,100]},{"i":{"x":[0.667,0.667,0.667],"y":[1,1,1]},"o":{"x":[0.167,0.167,0.167],"y":[0,0,0]},"t":115,"s":[100,5,100]},{"i":{"x":[0.311,0.301,0.667],"y":[1,1,1]},"o":{"x":[0.333,0.333,0.333],"y":[0,0,0]},"t":230,"s":[100,5,100]},{"t":248,"s":[100,100,100]}]}},"ao":0,"shapes":[{"ty":"gr","it":[{"ty":"rc","d":1,"s":{"a":0,"k":[64,101.053]},"p":{"a":0,"k":[0,0]},"r":{"a":0,"k":0},"nm":"Rectangle Path 1","hd":false},{"ty":"st","c":{"a":0,"k":[0.231372563979,0.211764720842,0.423529441684,1]},"o":{"a":0,"k":100},"w":{"a":0,"k":0},"lc":1,"lj":1,"ml":4,"bm":0,"nm":"Stroke 1","hd":false},{"ty":"fl","c":{"a":0,"k":[0.549019607843,0.541176470588,0.976470588235,1]},"o":{"a":0,"k":100},"r":1,"bm":0,"nm":"Fill 1","hd":false},{"ty":"tr","p":{"a":0,"k":[-629.25,112.25]},"a":{"a":0,"k":[0,0]},"s":{"a":0,"k":[100,100]},"r":{"a":0,"k":0},"o":{"a":0,"k":100},"sk":{"a":0,"k":0},"sa":{"a":0,"k":0},"nm":"Transform"}],"nm":"Rectangle 1","bm":0,"hd":false}],"ip":0,"op":775,"st":0,"ct":1,"bm":0},{"ddd":0,"ind":22,"ty":4,"nm":"1","sr":1,"ks":{"o":{"a":0,"k":50},"r":{"a":0,"k":0},"p":{"a":0,"k":[362.75,823.75,0]},"a":{"a":0,"k":[-629.25,162.8,0]},"s":{"a":1,"k":[{"i":{"x":[0.667,0.667,0.667],"y":[0.93,2.024,1]},"o":{"x":[0.333,0.333,0.333],"y":[0,0,0]},"t":98,"s":[100,100,100]},{"i":{"x":[0.651,0.49,0.667],"y":[1,1,1]},"o":{"x":[0.341,0.548,0.333],"y":[0.143,0.168,0]},"t":103,"s":[100,105,100]},{"i":{"x":[0.667,0.667,0.667],"y":[1,1,1]},"o":{"x":[0.167,0.167,0.167],"y":[0,0,0]},"t":113,"s":[100,5,100]},{"i":{"x":[0.311,0.301,0.667],"y":[1,1,1]},"o":{"x":[0.333,0.333,0.333],"y":[0,0,0]},"t":230,"s":[100,5,100]},{"t":248,"s":[100,100,100]}]}},"ao":0,"shapes":[{"ty":"gr","it":[{"ty":"rc","d":1,"s":{"a":0,"k":[64,101.053]},"p":{"a":0,"k":[0,0]},"r":{"a":0,"k":0},"nm":"Rectangle Path 1","hd":false},{"ty":"st","c":{"a":0,"k":[0.231372563979,0.211764720842,0.423529441684,1]},"o":{"a":0,"k":100},"w":{"a":0,"k":0},"lc":1,"lj":1,"ml":4,"bm":0,"nm":"Stroke 1","hd":false},{"ty":"fl","c":{"a":0,"k":[0.549019607843,0.541176470588,0.976470588235,1]},"o":{"a":0,"k":100},"r":1,"bm":0,"nm":"Fill 1","hd":false},{"ty":"tr","p":{"a":0,"k":[-629.25,112.25]},"a":{"a":0,"k":[0,0]},"s":{"a":0,"k":[100,100]},"r":{"a":0,"k":0},"o":{"a":0,"k":100},"sk":{"a":0,"k":0},"sa":{"a":0,"k":0},"nm":"Transform"}],"nm":"Rectangle 1","bm":0,"hd":false}],"ip":0,"op":775,"st":0,"ct":1,"bm":0},{"ddd":0,"ind":23,"ty":4,"nm":"infinite stroke7","parent":32,"sr":1,"ks":{"o":{"a":0,"k":100},"r":{"a":0,"k":0},"p":{"a":0,"k":[-559.234,-290,0]},"a":{"a":0,"k":[0,0,0]},"s":{"a":0,"k":[100,100,100]}},"ao":0,"shapes":[{"ty":"gr","it":[{"ind":0,"ty":"sh","ks":{"a":0,"k":{"i":[[8.562,0],[0,-15.812],[-5.562,0.375],[0,0],[-9.625,0],[0,11.562],[8.938,0],[0,0]],"o":[[-8.562,0],[0,15.812],[8.356,-0.563],[0,0],[9.625,0],[0,-11.562],[-8.938,0],[0,0]],"v":[[610.188,252],[590.312,271.75],[609.812,290.812],[623,285.938],[637.5,290.438],[655.688,271.438],[637.938,251.688],[623.062,256.25]],"c":true}},"nm":"Path 1","hd":false},{"ty":"st","c":{"a":0,"k":[0.541176470588,0.552941176471,0.968627510819,1]},"o":{"a":0,"k":100},"w":{"a":0,"k":2},"lc":1,"lj":1,"ml":4,"bm":0,"nm":"Stroke 1","hd":false},{"ty":"tr","p":{"a":0,"k":[0,0]},"a":{"a":0,"k":[0,0]},"s":{"a":0,"k":[100,100]},"r":{"a":0,"k":0},"o":{"a":0,"k":100},"sk":{"a":0,"k":0},"sa":{"a":0,"k":0},"nm":"Transform"}],"nm":"Shape 1","bm":0,"hd":false},{"ty":"tm","s":{"a":1,"k":[{"i":{"x":[0.433],"y":[1]},"o":{"x":[0.664],"y":[0]},"t":444,"s":[0]},{"t":455,"s":[100]}]},"e":{"a":1,"k":[{"i":{"x":[0.382],"y":[1]},"o":{"x":[0.752],"y":[0]},"t":439,"s":[0]},{"t":453,"s":[100]}]},"o":{"a":0,"k":0},"m":1,"nm":"Trim Paths 1","hd":false}],"ip":439,"op":456,"st":372,"ct":1,"bm":0},{"ddd":0,"ind":24,"ty":4,"nm":"infinite stroke6","parent":32,"sr":1,"ks":{"o":{"a":0,"k":100},"r":{"a":0,"k":0},"p":{"a":0,"k":[-559.234,-290,0]},"a":{"a":0,"k":[0,0,0]},"s":{"a":0,"k":[100,100,100]}},"ao":0,"shapes":[{"ty":"gr","it":[{"ind":0,"ty":"sh","ks":{"a":0,"k":{"i":[[8.562,0],[0,-15.812],[-5.562,0.375],[0,0],[-9.625,0],[0,11.562],[8.938,0],[0,0]],"o":[[-8.562,0],[0,15.812],[8.356,-0.563],[0,0],[9.625,0],[0,-11.562],[-8.938,0],[0,0]],"v":[[610.188,252],[590.312,271.75],[609.812,290.812],[623,285.938],[637.5,290.438],[655.688,271.438],[637.938,251.688],[623.062,256.25]],"c":true}},"nm":"Path 1","hd":false},{"ty":"st","c":{"a":0,"k":[0.541176470588,0.552941176471,0.968627510819,1]},"o":{"a":0,"k":100},"w":{"a":0,"k":2},"lc":1,"lj":1,"ml":4,"bm":0,"nm":"Stroke 1","hd":false},{"ty":"tr","p":{"a":0,"k":[0,0]},"a":{"a":0,"k":[0,0]},"s":{"a":0,"k":[100,100]},"r":{"a":0,"k":0},"o":{"a":0,"k":100},"sk":{"a":0,"k":0},"sa":{"a":0,"k":0},"nm":"Transform"}],"nm":"Shape 1","bm":0,"hd":false},{"ty":"tm","s":{"a":1,"k":[{"i":{"x":[0.433],"y":[1]},"o":{"x":[0.664],"y":[0]},"t":382,"s":[0]},{"t":393,"s":[100]}]},"e":{"a":1,"k":[{"i":{"x":[0.382],"y":[1]},"o":{"x":[0.752],"y":[0]},"t":377,"s":[0]},{"t":391,"s":[100]}]},"o":{"a":0,"k":0},"m":1,"nm":"Trim Paths 1","hd":false}],"ip":377,"op":394,"st":310,"ct":1,"bm":0},{"ddd":0,"ind":25,"ty":4,"nm":"infinite stroke5","parent":32,"sr":1,"ks":{"o":{"a":0,"k":100},"r":{"a":0,"k":0},"p":{"a":0,"k":[-559.234,-290,0]},"a":{"a":0,"k":[0,0,0]},"s":{"a":0,"k":[100,100,100]}},"ao":0,"shapes":[{"ty":"gr","it":[{"ind":0,"ty":"sh","ks":{"a":0,"k":{"i":[[8.562,0],[0,-15.812],[-5.562,0.375],[0,0],[-9.625,0],[0,11.562],[8.938,0],[0,0]],"o":[[-8.562,0],[0,15.812],[8.356,-0.563],[0,0],[9.625,0],[0,-11.562],[-8.938,0],[0,0]],"v":[[610.188,252],[590.312,271.75],[609.812,290.812],[623,285.938],[637.5,290.438],[655.688,271.438],[637.938,251.688],[623.062,256.25]],"c":true}},"nm":"Path 1","hd":false},{"ty":"st","c":{"a":0,"k":[0.541176470588,0.552941176471,0.968627510819,1]},"o":{"a":0,"k":100},"w":{"a":0,"k":2},"lc":1,"lj":1,"ml":4,"bm":0,"nm":"Stroke 1","hd":false},{"ty":"tr","p":{"a":0,"k":[0,0]},"a":{"a":0,"k":[0,0]},"s":{"a":0,"k":[100,100]},"r":{"a":0,"k":0},"o":{"a":0,"k":100},"sk":{"a":0,"k":0},"sa":{"a":0,"k":0},"nm":"Transform"}],"nm":"Shape 1","bm":0,"hd":false},{"ty":"tm","s":{"a":1,"k":[{"i":{"x":[0.433],"y":[1]},"o":{"x":[0.664],"y":[0]},"t":320,"s":[0]},{"t":331,"s":[100]}]},"e":{"a":1,"k":[{"i":{"x":[0.382],"y":[1]},"o":{"x":[0.752],"y":[0]},"t":315,"s":[0]},{"t":329,"s":[100]}]},"o":{"a":0,"k":0},"m":1,"nm":"Trim Paths 1","hd":false}],"ip":315,"op":332,"st":248,"ct":1,"bm":0},{"ddd":0,"ind":26,"ty":4,"nm":"infinite stroke4","parent":32,"sr":1,"ks":{"o":{"a":0,"k":100},"r":{"a":0,"k":0},"p":{"a":0,"k":[-559.234,-290,0]},"a":{"a":0,"k":[0,0,0]},"s":{"a":0,"k":[100,100,100]}},"ao":0,"shapes":[{"ty":"gr","it":[{"ind":0,"ty":"sh","ks":{"a":0,"k":{"i":[[8.562,0],[0,-15.812],[-5.562,0.375],[0,0],[-9.625,0],[0,11.562],[8.938,0],[0,0]],"o":[[-8.562,0],[0,15.812],[8.356,-0.563],[0,0],[9.625,0],[0,-11.562],[-8.938,0],[0,0]],"v":[[610.188,252],[590.312,271.75],[609.812,290.812],[623,285.938],[637.5,290.438],[655.688,271.438],[637.938,251.688],[623.062,256.25]],"c":true}},"nm":"Path 1","hd":false},{"ty":"st","c":{"a":0,"k":[0.541176470588,0.552941176471,0.968627510819,1]},"o":{"a":0,"k":100},"w":{"a":0,"k":2},"lc":1,"lj":1,"ml":4,"bm":0,"nm":"Stroke 1","hd":false},{"ty":"tr","p":{"a":0,"k":[0,0]},"a":{"a":0,"k":[0,0]},"s":{"a":0,"k":[100,100]},"r":{"a":0,"k":0},"o":{"a":0,"k":100},"sk":{"a":0,"k":0},"sa":{"a":0,"k":0},"nm":"Transform"}],"nm":"Shape 1","bm":0,"hd":false},{"ty":"tm","s":{"a":1,"k":[{"i":{"x":[0.433],"y":[1]},"o":{"x":[0.664],"y":[0]},"t":258,"s":[0]},{"t":269,"s":[100]}]},"e":{"a":1,"k":[{"i":{"x":[0.382],"y":[1]},"o":{"x":[0.752],"y":[0]},"t":253,"s":[0]},{"t":267,"s":[100]}]},"o":{"a":0,"k":0},"m":1,"nm":"Trim Paths 1","hd":false}],"ip":253,"op":270,"st":186,"ct":1,"bm":0},{"ddd":0,"ind":27,"ty":4,"nm":"infinite stroke3","parent":32,"sr":1,"ks":{"o":{"a":0,"k":100},"r":{"a":0,"k":0},"p":{"a":0,"k":[-559.234,-290,0]},"a":{"a":0,"k":[0,0,0]},"s":{"a":0,"k":[100,100,100]}},"ao":0,"shapes":[{"ty":"gr","it":[{"ind":0,"ty":"sh","ks":{"a":0,"k":{"i":[[8.562,0],[0,-15.812],[-5.562,0.375],[0,0],[-9.625,0],[0,11.562],[8.938,0],[0,0]],"o":[[-8.562,0],[0,15.812],[8.356,-0.563],[0,0],[9.625,0],[0,-11.562],[-8.938,0],[0,0]],"v":[[610.188,252],[590.312,271.75],[609.812,290.812],[623,285.938],[637.5,290.438],[655.688,271.438],[637.938,251.688],[623.062,256.25]],"c":true}},"nm":"Path 1","hd":false},{"ty":"st","c":{"a":0,"k":[0.541176470588,0.552941176471,0.968627510819,1]},"o":{"a":0,"k":100},"w":{"a":0,"k":2},"lc":1,"lj":1,"ml":4,"bm":0,"nm":"Stroke 1","hd":false},{"ty":"tr","p":{"a":0,"k":[0,0]},"a":{"a":0,"k":[0,0]},"s":{"a":0,"k":[100,100]},"r":{"a":0,"k":0},"o":{"a":0,"k":100},"sk":{"a":0,"k":0},"sa":{"a":0,"k":0},"nm":"Transform"}],"nm":"Shape 1","bm":0,"hd":false},{"ty":"tm","s":{"a":1,"k":[{"i":{"x":[0.433],"y":[1]},"o":{"x":[0.664],"y":[0]},"t":196,"s":[0]},{"t":207,"s":[100]}]},"e":{"a":1,"k":[{"i":{"x":[0.382],"y":[1]},"o":{"x":[0.752],"y":[0]},"t":191,"s":[0]},{"t":205,"s":[100]}]},"o":{"a":0,"k":0},"m":1,"nm":"Trim Paths 1","hd":false}],"ip":191,"op":208,"st":124,"ct":1,"bm":0},{"ddd":0,"ind":28,"ty":4,"nm":"infinite stroke 2","parent":32,"sr":1,"ks":{"o":{"a":0,"k":100},"r":{"a":0,"k":0},"p":{"a":0,"k":[-559.234,-290,0]},"a":{"a":0,"k":[0,0,0]},"s":{"a":0,"k":[100,100,100]}},"ao":0,"shapes":[{"ty":"gr","it":[{"ind":0,"ty":"sh","ks":{"a":0,"k":{"i":[[8.562,0],[0,-15.812],[-5.562,0.375],[0,0],[-9.625,0],[0,11.562],[8.938,0],[0,0]],"o":[[-8.562,0],[0,15.812],[8.356,-0.563],[0,0],[9.625,0],[0,-11.562],[-8.938,0],[0,0]],"v":[[610.188,252],[590.312,271.75],[609.812,290.812],[623,285.938],[637.5,290.438],[655.688,271.438],[637.938,251.688],[623.062,256.25]],"c":true}},"nm":"Path 1","hd":false},{"ty":"st","c":{"a":0,"k":[0.541176470588,0.552941176471,0.968627510819,1]},"o":{"a":0,"k":100},"w":{"a":0,"k":2},"lc":1,"lj":1,"ml":4,"bm":0,"nm":"Stroke 1","hd":false},{"ty":"tr","p":{"a":0,"k":[0,0]},"a":{"a":0,"k":[0,0]},"s":{"a":0,"k":[100,100]},"r":{"a":0,"k":0},"o":{"a":0,"k":100},"sk":{"a":0,"k":0},"sa":{"a":0,"k":0},"nm":"Transform"}],"nm":"Shape 1","bm":0,"hd":false},{"ty":"tm","s":{"a":1,"k":[{"i":{"x":[0.433],"y":[1]},"o":{"x":[0.664],"y":[0]},"t":134,"s":[0]},{"t":145,"s":[100]}]},"e":{"a":1,"k":[{"i":{"x":[0.382],"y":[1]},"o":{"x":[0.752],"y":[0]},"t":129,"s":[0]},{"t":143,"s":[100]}]},"o":{"a":0,"k":0},"m":1,"nm":"Trim Paths 1","hd":false}],"ip":129,"op":146,"st":62,"ct":1,"bm":0},{"ddd":0,"ind":29,"ty":4,"nm":"infinite stroke2","parent":32,"sr":1,"ks":{"o":{"a":0,"k":100},"r":{"a":0,"k":0},"p":{"a":0,"k":[-559.234,-290,0]},"a":{"a":0,"k":[0,0,0]},"s":{"a":0,"k":[100,100,100]}},"ao":0,"shapes":[{"ty":"gr","it":[{"ind":0,"ty":"sh","ks":{"a":0,"k":{"i":[[8.562,0],[0,-15.812],[-5.562,0.375],[0,0],[-9.625,0],[0,11.562],[8.938,0],[0,0]],"o":[[-8.562,0],[0,15.812],[8.356,-0.563],[0,0],[9.625,0],[0,-11.562],[-8.938,0],[0,0]],"v":[[610.188,252],[590.312,271.75],[609.812,290.812],[623,285.938],[637.5,290.438],[655.688,271.438],[637.938,251.688],[623.062,256.25]],"c":true}},"nm":"Path 1","hd":false},{"ty":"st","c":{"a":0,"k":[0.541176470588,0.552941176471,0.968627510819,1]},"o":{"a":0,"k":100},"w":{"a":0,"k":2},"lc":1,"lj":1,"ml":4,"bm":0,"nm":"Stroke 1","hd":false},{"ty":"tr","p":{"a":0,"k":[0,0]},"a":{"a":0,"k":[0,0]},"s":{"a":0,"k":[100,100]},"r":{"a":0,"k":0},"o":{"a":0,"k":100},"sk":{"a":0,"k":0},"sa":{"a":0,"k":0},"nm":"Transform"}],"nm":"Shape 1","bm":0,"hd":false},{"ty":"tm","s":{"a":1,"k":[{"i":{"x":[0.433],"y":[1]},"o":{"x":[0.664],"y":[0]},"t":72,"s":[0]},{"t":83,"s":[100]}]},"e":{"a":1,"k":[{"i":{"x":[0.382],"y":[1]},"o":{"x":[0.752],"y":[0]},"t":67,"s":[0]},{"t":81,"s":[100]}]},"o":{"a":0,"k":0},"m":1,"nm":"Trim Paths 1","hd":false}],"ip":67,"op":84,"st":0,"ct":1,"bm":0},{"ddd":0,"ind":30,"ty":4,"nm":"infinite stroke","parent":32,"sr":1,"ks":{"o":{"a":0,"k":100},"r":{"a":0,"k":0},"p":{"a":0,"k":[-559.234,-290,0]},"a":{"a":0,"k":[0,0,0]},"s":{"a":0,"k":[100,100,100]}},"ao":0,"shapes":[{"ty":"gr","it":[{"ind":0,"ty":"sh","ks":{"a":0,"k":{"i":[[8.562,0],[0,-15.812],[-5.562,0.375],[0,0],[-9.625,0],[0,11.562],[8.938,0],[0,0]],"o":[[-8.562,0],[0,15.812],[8.356,-0.563],[0,0],[9.625,0],[0,-11.562],[-8.938,0],[0,0]],"v":[[610.188,252],[590.312,271.75],[609.812,290.812],[623,285.938],[637.5,290.438],[655.688,271.438],[637.938,251.688],[623.062,256.25]],"c":true}},"nm":"Path 1","hd":false},{"ty":"st","c":{"a":0,"k":[0.541176470588,0.552941176471,0.968627510819,1]},"o":{"a":0,"k":100},"w":{"a":0,"k":2},"lc":1,"lj":1,"ml":4,"bm":0,"nm":"Stroke 1","hd":false},{"ty":"tr","p":{"a":0,"k":[0,0]},"a":{"a":0,"k":[0,0]},"s":{"a":0,"k":[100,100]},"r":{"a":0,"k":0},"o":{"a":0,"k":100},"sk":{"a":0,"k":0},"sa":{"a":0,"k":0},"nm":"Transform"}],"nm":"Shape 1","bm":0,"hd":false},{"ty":"tm","s":{"a":1,"k":[{"i":{"x":[0.433],"y":[1]},"o":{"x":[0.664],"y":[0]},"t":10,"s":[0]},{"t":21,"s":[100]}]},"e":{"a":1,"k":[{"i":{"x":[0.382],"y":[1]},"o":{"x":[0.752],"y":[0]},"t":5,"s":[0]},{"t":19,"s":[100]}]},"o":{"a":0,"k":0},"m":1,"nm":"Trim Paths 1","hd":false}],"ip":5,"op":22,"st":-62,"ct":1,"bm":0},{"ddd":0,"ind":31,"ty":4,"nm":"infinite","sr":1,"ks":{"o":{"a":0,"k":100},"r":{"a":0,"k":0},"p":{"a":0,"k":[1583.146,911.463,0]},"a":{"a":0,"k":[63.912,-18.537,0]},"s":{"a":1,"k":[{"i":{"x":[0.833,0.833,0.833],"y":[0.833,0.833,0.833]},"o":{"x":[0.167,0.167,0.167],"y":[0.167,0.167,0.167]},"t":11,"s":[100,100,100]},{"i":{"x":[0.667,0.667,0.667],"y":[1,1,1]},"o":{"x":[0.167,0.167,0.167],"y":[0.167,0.167,1.333]},"t":15,"s":[115,115,100]},{"i":{"x":[0.833,0.833,0.833],"y":[1,1,1]},"o":{"x":[0.167,0.167,0.167],"y":[0,0,0]},"t":32,"s":[100,100,100]},{"i":{"x":[0.833,0.833,0.833],"y":[0.833,0.833,0.833]},"o":{"x":[0.167,0.167,0.167],"y":[0.167,0.167,0.167]},"t":72,"s":[100,100,100]},{"i":{"x":[0.667,0.667,0.667],"y":[1,1,1]},"o":{"x":[0.167,0.167,0.167],"y":[0.167,0.167,0]},"t":76,"s":[115,115,100]},{"i":{"x":[0.833,0.833,0.833],"y":[1,1,1]},"o":{"x":[0.167,0.167,0.167],"y":[0,0,0]},"t":93,"s":[100,100,100]},{"i":{"x":[0.833,0.833,0.833],"y":[0.833,0.833,0.833]},"o":{"x":[0.167,0.167,0.167],"y":[0.167,0.167,0.167]},"t":133,"s":[100,100,100]},{"i":{"x":[0.667,0.667,0.667],"y":[1,1,1]},"o":{"x":[0.167,0.167,0.167],"y":[0.167,0.167,0]},"t":137,"s":[115,115,100]},{"i":{"x":[0.833,0.833,0.833],"y":[1,1,1]},"o":{"x":[0.167,0.167,0.167],"y":[0,0,0]},"t":154,"s":[100,100,100]},{"i":{"x":[0.833,0.833,0.833],"y":[0.833,0.833,0.833]},"o":{"x":[0.167,0.167,0.167],"y":[0.167,0.167,0.167]},"t":195,"s":[100,100,100]},{"i":{"x":[0.667,0.667,0.667],"y":[1,1,1]},"o":{"x":[0.167,0.167,0.167],"y":[0.167,0.167,0]},"t":199,"s":[115,115,100]},{"i":{"x":[0.833,0.833,0.833],"y":[1,1,1]},"o":{"x":[0.167,0.167,0.167],"y":[0,0,0]},"t":216,"s":[100,100,100]},{"i":{"x":[0.833,0.833,0.833],"y":[0.833,0.833,0.833]},"o":{"x":[0.167,0.167,0.167],"y":[0.167,0.167,0.167]},"t":257,"s":[100,100,100]},{"i":{"x":[0.667,0.667,0.667],"y":[1,1,1]},"o":{"x":[0.167,0.167,0.167],"y":[0.167,0.167,0]},"t":261,"s":[115,115,100]},{"i":{"x":[0.833,0.833,0.833],"y":[1,1,1]},"o":{"x":[0.167,0.167,0.167],"y":[0,0,0]},"t":278,"s":[100,100,100]},{"i":{"x":[0.833,0.833,0.833],"y":[0.833,0.833,0.833]},"o":{"x":[0.167,0.167,0.167],"y":[0.167,0.167,0.167]},"t":319,"s":[100,100,100]},{"i":{"x":[0.667,0.667,0.667],"y":[1,1,1]},"o":{"x":[0.167,0.167,0.167],"y":[0.167,0.167,0]},"t":323,"s":[115,115,100]},{"i":{"x":[0.833,0.833,0.833],"y":[1,1,1]},"o":{"x":[0.167,0.167,0.167],"y":[0,0,0]},"t":340,"s":[100,100,100]},{"i":{"x":[0.833,0.833,0.833],"y":[0.833,0.833,0.833]},"o":{"x":[0.167,0.167,0.167],"y":[0.167,0.167,0.167]},"t":382,"s":[100,100,100]},{"i":{"x":[0.667,0.667,0.667],"y":[1,1,1]},"o":{"x":[0.167,0.167,0.167],"y":[0.167,0.167,0]},"t":386,"s":[115,115,100]},{"i":{"x":[0.833,0.833,0.833],"y":[1,1,1]},"o":{"x":[0.167,0.167,0.167],"y":[0,0,0]},"t":403,"s":[100,100,100]},{"i":{"x":[0.833,0.833,0.833],"y":[0.833,0.833,0.833]},"o":{"x":[0.167,0.167,0.167],"y":[0.167,0.167,0.167]},"t":443,"s":[100,100,100]},{"i":{"x":[0.667,0.667,0.667],"y":[1,1,1]},"o":{"x":[0.167,0.167,0.167],"y":[0.167,0.167,0]},"t":447,"s":[115,115,100]},{"t":464,"s":[100,100,100]}]}},"ao":0,"shapes":[{"ty":"gr","it":[{"ind":0,"ty":"sh","ks":{"a":0,"k":{"i":[[1.428,-0.604],[1.072,-1.065],[0.604,-1.413],[0,-1.619],[-1.051,-1.775],[-1.776,-1.051],[-2.188,0],[-1.286,0.447],[-1.044,0.703],[-0.796,0.767],[-0.433,0.504],[-0.384,0.469],[-0.426,-0.504],[-0.511,-0.511],[-1.044,-0.703],[-1.3,-0.447],[-1.563,0],[-1.414,0.604],[-1.065,1.073],[-0.604,1.428],[0,1.634],[1.044,1.768],[1.768,1.044],[2.159,0],[1.754,-0.966],[1.193,-1.193],[0.384,-0.454],[0.341,-0.469],[0.433,0.497],[0.511,0.469],[1.044,0.717],[1.285,0.447],[1.534,0]],"o":[[-1.428,0.604],[-1.073,1.065],[-0.604,1.414],[0,2.188],[1.051,1.776],[1.775,1.051],[1.534,0],[1.285,-0.447],[1.044,-0.703],[0.511,-0.511],[0.433,-0.504],[0.341,0.469],[0.426,0.504],[0.795,0.767],[1.044,0.703],[1.3,0.447],[1.619,0],[1.413,-0.604],[1.065,-1.072],[0.604,-1.428],[0,-2.159],[-1.044,-1.768],[-1.768,-1.044],[-2.344,0],[-1.754,0.966],[-0.597,0.554],[-0.384,0.455],[-0.384,-0.469],[-0.433,-0.497],[-0.796,-0.795],[-1.044,-0.717],[-1.286,-0.447],[-1.634,0]],"v":[[46.238,-29.35],[42.488,-26.847],[39.974,-23.129],[39.068,-18.58],[40.645,-12.635],[44.885,-8.395],[50.83,-6.818],[55.059,-7.489],[58.553,-9.215],[61.312,-11.42],[62.729,-12.944],[63.955,-14.403],[65.105,-12.944],[66.511,-11.42],[69.271,-9.215],[72.786,-7.489],[77.08,-6.818],[81.629,-7.724],[85.347,-10.238],[87.85,-13.988],[88.756,-18.58],[87.19,-24.471],[82.971,-28.69],[77.08,-30.256],[70.933,-28.807],[66.511,-25.568],[65.041,-24.055],[63.955,-22.67],[62.729,-24.119],[61.312,-25.568],[58.553,-27.837],[55.059,-29.585],[50.83,-30.256]],"c":true}},"nm":"","hd":false},{"ind":1,"ty":"sh","ks":{"a":0,"k":{"i":[[-0.618,1.03],[-1.044,0.618],[-1.278,0],[-1.186,-0.639],[-0.938,-0.938],[-0.462,-0.589],[-0.384,-0.511],[0.483,-0.597],[0.639,-0.639],[1.165,-0.639],[1.406,0],[1.044,0.618],[0.618,1.044],[0,1.278]],"o":[[0.618,-1.03],[1.044,-0.618],[1.406,0],[1.186,0.639],[0.682,0.639],[0.461,0.59],[-0.384,0.554],[-0.483,0.597],[-0.98,0.938],[-1.165,0.639],[-1.278,0],[-1.044,-0.618],[-0.618,-1.044],[0,-1.25]],"v":[[44.853,-21.999],[47.346,-24.471],[50.83,-25.398],[54.718,-24.439],[57.903,-22.074],[59.619,-20.231],[60.886,-18.58],[59.587,-16.854],[57.903,-15],[54.686,-12.635],[50.83,-11.676],[47.346,-12.603],[44.853,-15.096],[43.926,-18.58]],"c":true}},"nm":"","hd":false},{"ind":2,"ty":"sh","ks":{"a":0,"k":{"i":[[0.618,-1.044],[1.03,-0.618],[1.25,0],[1.172,0.639],[0.98,0.938],[0.483,0.597],[0.384,0.554],[-0.504,0.675],[-0.767,0.724],[-0.739,0.504],[-0.852,0.291],[-0.966,0],[-1.03,-0.618],[-0.618,-1.03],[0,-1.25]],"o":[[-0.618,1.044],[-1.03,0.618],[-1.449,0],[-1.172,-0.639],[-0.639,-0.639],[-0.483,-0.597],[0.213,-0.256],[0.504,-0.674],[0.625,-0.625],[0.738,-0.504],[0.852,-0.291],[1.25,0],[1.03,0.618],[0.618,1.03],[0,1.278]],"v":[[82.971,-15.096],[80.499,-12.603],[77.08,-11.676],[73.148,-12.635],[69.92,-15],[68.237,-16.854],[66.938,-18.58],[68.014,-19.975],[69.92,-22.074],[71.966,-23.768],[74.352,-24.961],[77.08,-25.398],[80.499,-24.471],[82.971,-21.999],[83.898,-18.58]],"c":true}},"nm":"","hd":false},{"ty":"mm","mm":1,"nm":"Merge Paths 1","hd":false},{"ty":"fl","c":{"a":0,"k":[1,1,1,1]},"o":{"a":0,"k":100},"r":1,"bm":0,"nm":"Fill 1","hd":false},{"ty":"st","c":{"a":0,"k":[0,0,0,1]},"o":{"a":0,"k":100},"w":{"a":0,"k":0.01},"lc":1,"lj":1,"ml":4,"bm":0,"nm":"Stroke 1","hd":false},{"ty":"tr","p":{"a":0,"k":[0,0]},"a":{"a":0,"k":[0,0]},"s":{"a":0,"k":[100,100]},"r":{"a":0,"k":0},"o":{"a":0,"k":100},"sk":{"a":0,"k":0},"sa":{"a":0,"k":0},"nm":"Transform"}],"nm":"","bm":0,"hd":false}],"ip":0,"op":775,"st":0,"ct":1,"bm":0},{"ddd":0,"ind":32,"ty":4,"nm":"infinite shine","sr":1,"ks":{"o":{"a":1,"k":[{"i":{"x":[0.833],"y":[0.833]},"o":{"x":[0.167],"y":[0.167]},"t":20,"s":[0]},{"i":{"x":[0.833],"y":[0.833]},"o":{"x":[0.167],"y":[0.167]},"t":28,"s":[100]},{"i":{"x":[0.833],"y":[0.833]},"o":{"x":[0.167],"y":[0.167]},"t":43,"s":[0]},{"i":{"x":[0.833],"y":[0.833]},"o":{"x":[0.167],"y":[0.167]},"t":80,"s":[0]},{"i":{"x":[0.833],"y":[0.833]},"o":{"x":[0.167],"y":[0.167]},"t":88,"s":[100]},{"i":{"x":[0.833],"y":[0.833]},"o":{"x":[0.167],"y":[0.167]},"t":103,"s":[0]},{"i":{"x":[0.833],"y":[0.833]},"o":{"x":[0.167],"y":[0.167]},"t":141,"s":[0]},{"i":{"x":[0.833],"y":[0.833]},"o":{"x":[0.167],"y":[0.167]},"t":149,"s":[100]},{"i":{"x":[0.833],"y":[0.833]},"o":{"x":[0.167],"y":[0.167]},"t":164,"s":[0]},{"i":{"x":[0.833],"y":[0.833]},"o":{"x":[0.167],"y":[0.167]},"t":203,"s":[0]},{"i":{"x":[0.833],"y":[0.833]},"o":{"x":[0.167],"y":[0.167]},"t":211,"s":[100]},{"i":{"x":[0.833],"y":[0.833]},"o":{"x":[0.167],"y":[0.167]},"t":226,"s":[0]},{"i":{"x":[0.833],"y":[0.833]},"o":{"x":[0.167],"y":[0.167]},"t":265,"s":[0]},{"i":{"x":[0.833],"y":[0.833]},"o":{"x":[0.167],"y":[0.167]},"t":273,"s":[100]},{"i":{"x":[0.833],"y":[0.833]},"o":{"x":[0.167],"y":[0.167]},"t":288,"s":[0]},{"i":{"x":[0.833],"y":[0.833]},"o":{"x":[0.167],"y":[0.167]},"t":327,"s":[0]},{"i":{"x":[0.833],"y":[0.833]},"o":{"x":[0.167],"y":[0.167]},"t":335,"s":[100]},{"i":{"x":[0.833],"y":[0.833]},"o":{"x":[0.167],"y":[0.167]},"t":350,"s":[0]},{"i":{"x":[0.833],"y":[0.833]},"o":{"x":[0.167],"y":[0.167]},"t":390,"s":[0]},{"i":{"x":[0.833],"y":[0.833]},"o":{"x":[0.167],"y":[0.167]},"t":398,"s":[100]},{"i":{"x":[0.833],"y":[0.833]},"o":{"x":[0.167],"y":[0.167]},"t":413,"s":[0]},{"i":{"x":[0.833],"y":[0.833]},"o":{"x":[0.167],"y":[0.167]},"t":451,"s":[0]},{"i":{"x":[0.833],"y":[0.833]},"o":{"x":[0.167],"y":[0.167]},"t":459,"s":[100]},{"t":474,"s":[0]}]},"r":{"a":0,"k":0},"p":{"a":0,"k":[1583.146,911.463,0]},"a":{"a":0,"k":[63.912,-18.537,0]},"s":{"a":1,"k":[{"i":{"x":[0.833,0.833,0.833],"y":[0.833,0.833,0.833]},"o":{"x":[0.167,0.167,0.167],"y":[0.167,0.167,0.167]},"t":11,"s":[100,100,100]},{"i":{"x":[0.667,0.667,0.667],"y":[1,1,1]},"o":{"x":[0.167,0.167,0.167],"y":[0.167,0.167,1.333]},"t":15,"s":[115,115,100]},{"i":{"x":[0.833,0.833,0.833],"y":[1,1,1]},"o":{"x":[0.167,0.167,0.167],"y":[0,0,0]},"t":32,"s":[100,100,100]},{"i":{"x":[0.833,0.833,0.833],"y":[0.833,0.833,0.833]},"o":{"x":[0.167,0.167,0.167],"y":[0.167,0.167,0.167]},"t":72,"s":[100,100,100]},{"i":{"x":[0.667,0.667,0.667],"y":[1,1,1]},"o":{"x":[0.167,0.167,0.167],"y":[0.167,0.167,0]},"t":76,"s":[115,115,100]},{"i":{"x":[0.833,0.833,0.833],"y":[1,1,1]},"o":{"x":[0.167,0.167,0.167],"y":[0,0,0]},"t":93,"s":[100,100,100]},{"i":{"x":[0.833,0.833,0.833],"y":[0.833,0.833,0.833]},"o":{"x":[0.167,0.167,0.167],"y":[0.167,0.167,0.167]},"t":133,"s":[100,100,100]},{"i":{"x":[0.667,0.667,0.667],"y":[1,1,1]},"o":{"x":[0.167,0.167,0.167],"y":[0.167,0.167,0]},"t":137,"s":[115,115,100]},{"i":{"x":[0.833,0.833,0.833],"y":[1,1,1]},"o":{"x":[0.167,0.167,0.167],"y":[0,0,0]},"t":154,"s":[100,100,100]},{"i":{"x":[0.833,0.833,0.833],"y":[0.833,0.833,0.833]},"o":{"x":[0.167,0.167,0.167],"y":[0.167,0.167,0.167]},"t":195,"s":[100,100,100]},{"i":{"x":[0.667,0.667,0.667],"y":[1,1,1]},"o":{"x":[0.167,0.167,0.167],"y":[0.167,0.167,0]},"t":199,"s":[115,115,100]},{"i":{"x":[0.833,0.833,0.833],"y":[1,1,1]},"o":{"x":[0.167,0.167,0.167],"y":[0,0,0]},"t":216,"s":[100,100,100]},{"i":{"x":[0.833,0.833,0.833],"y":[0.833,0.833,0.833]},"o":{"x":[0.167,0.167,0.167],"y":[0.167,0.167,0.167]},"t":257,"s":[100,100,100]},{"i":{"x":[0.667,0.667,0.667],"y":[1,1,1]},"o":{"x":[0.167,0.167,0.167],"y":[0.167,0.167,0]},"t":261,"s":[115,115,100]},{"i":{"x":[0.833,0.833,0.833],"y":[1,1,1]},"o":{"x":[0.167,0.167,0.167],"y":[0,0,0]},"t":278,"s":[100,100,100]},{"i":{"x":[0.833,0.833,0.833],"y":[0.833,0.833,0.833]},"o":{"x":[0.167,0.167,0.167],"y":[0.167,0.167,0.167]},"t":319,"s":[100,100,100]},{"i":{"x":[0.667,0.667,0.667],"y":[1,1,1]},"o":{"x":[0.167,0.167,0.167],"y":[0.167,0.167,0]},"t":323,"s":[115,115,100]},{"i":{"x":[0.833,0.833,0.833],"y":[1,1,1]},"o":{"x":[0.167,0.167,0.167],"y":[0,0,0]},"t":340,"s":[100,100,100]},{"i":{"x":[0.833,0.833,0.833],"y":[0.833,0.833,0.833]},"o":{"x":[0.167,0.167,0.167],"y":[0.167,0.167,0.167]},"t":382,"s":[100,100,100]},{"i":{"x":[0.667,0.667,0.667],"y":[1,1,1]},"o":{"x":[0.167,0.167,0.167],"y":[0.167,0.167,0]},"t":386,"s":[115,115,100]},{"i":{"x":[0.833,0.833,0.833],"y":[1,1,1]},"o":{"x":[0.167,0.167,0.167],"y":[0,0,0]},"t":403,"s":[100,100,100]},{"i":{"x":[0.833,0.833,0.833],"y":[0.833,0.833,0.833]},"o":{"x":[0.167,0.167,0.167],"y":[0.167,0.167,0.167]},"t":443,"s":[100,100,100]},{"i":{"x":[0.667,0.667,0.667],"y":[1,1,1]},"o":{"x":[0.167,0.167,0.167],"y":[0.167,0.167,0]},"t":447,"s":[115,115,100]},{"t":464,"s":[100,100,100]}]}},"ao":0,"ef":[{"ty":29,"nm":"Gaussian Blur","np":5,"mn":"ADBE Gaussian Blur 2","ix":1,"en":1,"ef":[{"ty":0,"nm":"Blurriness","mn":"ADBE Gaussian Blur 2-0001","ix":1,"v":{"a":0,"k":14.8}},{"ty":7,"nm":"Blur Dimensions","mn":"ADBE Gaussian Blur 2-0002","ix":2,"v":{"a":0,"k":1}},{"ty":7,"nm":"Repeat Edge Pixels","mn":"ADBE Gaussian Blur 2-0003","ix":3,"v":{"a":0,"k":0}}]}],"shapes":[{"ty":"gr","it":[{"ind":0,"ty":"sh","ks":{"a":0,"k":{"i":[[1.428,-0.604],[1.072,-1.065],[0.604,-1.413],[0,-1.619],[-1.051,-1.775],[-1.776,-1.051],[-2.188,0],[-1.286,0.447],[-1.044,0.703],[-0.796,0.767],[-0.433,0.504],[-0.384,0.469],[-0.426,-0.504],[-0.511,-0.511],[-1.044,-0.703],[-1.3,-0.447],[-1.563,0],[-1.414,0.604],[-1.065,1.073],[-0.604,1.428],[0,1.634],[1.044,1.768],[1.768,1.044],[2.159,0],[1.754,-0.966],[1.193,-1.193],[0.384,-0.454],[0.341,-0.469],[0.433,0.497],[0.511,0.469],[1.044,0.717],[1.285,0.447],[1.534,0]],"o":[[-1.428,0.604],[-1.073,1.065],[-0.604,1.414],[0,2.188],[1.051,1.776],[1.775,1.051],[1.534,0],[1.285,-0.447],[1.044,-0.703],[0.511,-0.511],[0.433,-0.504],[0.341,0.469],[0.426,0.504],[0.795,0.767],[1.044,0.703],[1.3,0.447],[1.619,0],[1.413,-0.604],[1.065,-1.072],[0.604,-1.428],[0,-2.159],[-1.044,-1.768],[-1.768,-1.044],[-2.344,0],[-1.754,0.966],[-0.597,0.554],[-0.384,0.455],[-0.384,-0.469],[-0.433,-0.497],[-0.796,-0.795],[-1.044,-0.717],[-1.286,-0.447],[-1.634,0]],"v":[[46.238,-29.35],[42.488,-26.847],[39.974,-23.129],[39.068,-18.58],[40.645,-12.635],[44.885,-8.395],[50.83,-6.818],[55.059,-7.489],[58.553,-9.215],[61.312,-11.42],[62.729,-12.944],[63.955,-14.403],[65.105,-12.944],[66.511,-11.42],[69.271,-9.215],[72.786,-7.489],[77.08,-6.818],[81.629,-7.724],[85.347,-10.238],[87.85,-13.988],[88.756,-18.58],[87.19,-24.471],[82.971,-28.69],[77.08,-30.256],[70.933,-28.807],[66.511,-25.568],[65.041,-24.055],[63.955,-22.67],[62.729,-24.119],[61.312,-25.568],[58.553,-27.837],[55.059,-29.585],[50.83,-30.256]],"c":true}},"nm":"","hd":false},{"ind":1,"ty":"sh","ks":{"a":0,"k":{"i":[[-0.618,1.03],[-1.044,0.618],[-1.278,0],[-1.186,-0.639],[-0.938,-0.938],[-0.462,-0.589],[-0.384,-0.511],[0.483,-0.597],[0.639,-0.639],[1.165,-0.639],[1.406,0],[1.044,0.618],[0.618,1.044],[0,1.278]],"o":[[0.618,-1.03],[1.044,-0.618],[1.406,0],[1.186,0.639],[0.682,0.639],[0.461,0.59],[-0.384,0.554],[-0.483,0.597],[-0.98,0.938],[-1.165,0.639],[-1.278,0],[-1.044,-0.618],[-0.618,-1.044],[0,-1.25]],"v":[[44.853,-21.999],[47.346,-24.471],[50.83,-25.398],[54.718,-24.439],[57.903,-22.074],[59.619,-20.231],[60.886,-18.58],[59.587,-16.854],[57.903,-15],[54.686,-12.635],[50.83,-11.676],[47.346,-12.603],[44.853,-15.096],[43.926,-18.58]],"c":true}},"nm":"","hd":false},{"ind":2,"ty":"sh","ks":{"a":0,"k":{"i":[[0.618,-1.044],[1.03,-0.618],[1.25,0],[1.172,0.639],[0.98,0.938],[0.483,0.597],[0.384,0.554],[-0.504,0.675],[-0.767,0.724],[-0.739,0.504],[-0.852,0.291],[-0.966,0],[-1.03,-0.618],[-0.618,-1.03],[0,-1.25]],"o":[[-0.618,1.044],[-1.03,0.618],[-1.449,0],[-1.172,-0.639],[-0.639,-0.639],[-0.483,-0.597],[0.213,-0.256],[0.504,-0.674],[0.625,-0.625],[0.738,-0.504],[0.852,-0.291],[1.25,0],[1.03,0.618],[0.618,1.03],[0,1.278]],"v":[[82.971,-15.096],[80.499,-12.603],[77.08,-11.676],[73.148,-12.635],[69.92,-15],[68.237,-16.854],[66.938,-18.58],[68.014,-19.975],[69.92,-22.074],[71.966,-23.768],[74.352,-24.961],[77.08,-25.398],[80.499,-24.471],[82.971,-21.999],[83.898,-18.58]],"c":true}},"nm":"","hd":false},{"ty":"mm","mm":1,"nm":"Merge Paths 1","hd":false},{"ty":"gf","o":{"a":0,"k":100},"r":1,"bm":0,"g":{"p":5,"k":{"a":0,"k":[0.005,0.161,0.816,0.698,0.251,0.487,0.871,0.802,0.497,0.813,0.925,0.905,0.727,0.487,0.871,0.802,0.957,0.161,0.816,0.698]}},"s":{"a":0,"k":[105,2.5]},"e":{"a":0,"k":[183.5,34]},"t":1,"nm":"Gradient Fill 1","hd":false},{"ty":"fl","c":{"a":0,"k":[1,1,1,1]},"o":{"a":0,"k":100},"r":1,"bm":0,"nm":"Fill 1","hd":false},{"ty":"st","c":{"a":0,"k":[0,0,0,1]},"o":{"a":0,"k":100},"w":{"a":0,"k":0.01},"lc":1,"lj":1,"ml":4,"bm":0,"nm":"Stroke 1","hd":false},{"ty":"tr","p":{"a":0,"k":[0,0]},"a":{"a":0,"k":[0,0]},"s":{"a":0,"k":[100,100]},"r":{"a":0,"k":0},"o":{"a":0,"k":100},"sk":{"a":0,"k":0},"sa":{"a":0,"k":0},"nm":"Transform"}],"nm":"","bm":0,"hd":false}],"ip":0,"op":775,"st":0,"ct":1,"bm":0},{"ddd":0,"ind":33,"ty":4,"nm":"0 stroke7","parent":41,"sr":1,"ks":{"o":{"a":0,"k":100},"r":{"a":0,"k":0},"p":{"a":0,"k":[20.037,-21.719,0]},"a":{"a":0,"k":[19.449,-21.877,0]},"s":{"a":0,"k":[196,152,100]}},"ao":0,"shapes":[{"ty":"gr","it":[{"ind":0,"ty":"sh","ks":{"a":0,"k":{"i":[[-1.911,1.557],[-1.012,2.958],[0,4.191],[1.018,2.946],[1.911,1.557],[2.673,0],[1.917,-1.551],[1.018,-2.952],[0,-4.165],[-1.012,-2.965],[-1.911,-1.551],[-2.696,0]],"o":[[1.911,-1.557],[1.012,-2.958],[0,-4.165],[-1.018,-2.946],[-1.911,-1.557],[-2.673,0],[-1.917,1.551],[-1.018,2.952],[0,4.178],[1.012,2.965],[1.911,1.551],[2.685,0]],"v":[[26.281,-4.295],[30.666,-11.069],[32.185,-21.792],[30.658,-32.459],[26.264,-39.213],[19.387,-41.549],[12.502,-39.223],[8.099,-32.468],[6.572,-21.792],[8.091,-11.078],[12.476,-4.304],[19.387,-1.959]],"c":true}},"nm":"0","hd":false},{"ty":"mm","mm":1,"nm":"Merge Paths 1","hd":false},{"ty":"st","c":{"a":0,"k":[0.541176470588,0.552941176471,0.968627510819,1]},"o":{"a":0,"k":100},"w":{"a":0,"k":1},"lc":1,"lj":1,"ml":4,"bm":0,"nm":"Stroke 1","hd":false},{"ty":"tr","p":{"a":0,"k":[0,0]},"a":{"a":0,"k":[0,0]},"s":{"a":0,"k":[100,100]},"r":{"a":0,"k":0},"o":{"a":0,"k":100},"sk":{"a":0,"k":0},"sa":{"a":0,"k":0},"nm":"Transform"}],"nm":"0","bm":0,"hd":false},{"ty":"tm","s":{"a":1,"k":[{"i":{"x":[0.433],"y":[1]},"o":{"x":[0.664],"y":[0]},"t":404,"s":[0]},{"t":415,"s":[100]}]},"e":{"a":1,"k":[{"i":{"x":[0.382],"y":[1]},"o":{"x":[0.752],"y":[0]},"t":399,"s":[0]},{"t":413,"s":[100]}]},"o":{"a":0,"k":0},"m":1,"nm":"Trim Paths 1","hd":false}],"ip":398,"op":416,"st":372,"ct":1,"bm":0},{"ddd":0,"ind":34,"ty":4,"nm":"0 stroke6","parent":41,"sr":1,"ks":{"o":{"a":0,"k":100},"r":{"a":0,"k":0},"p":{"a":0,"k":[20.037,-21.719,0]},"a":{"a":0,"k":[19.449,-21.877,0]},"s":{"a":0,"k":[196,152,100]}},"ao":0,"shapes":[{"ty":"gr","it":[{"ind":0,"ty":"sh","ks":{"a":0,"k":{"i":[[-1.911,1.557],[-1.012,2.958],[0,4.191],[1.018,2.946],[1.911,1.557],[2.673,0],[1.917,-1.551],[1.018,-2.952],[0,-4.165],[-1.012,-2.965],[-1.911,-1.551],[-2.696,0]],"o":[[1.911,-1.557],[1.012,-2.958],[0,-4.165],[-1.018,-2.946],[-1.911,-1.557],[-2.673,0],[-1.917,1.551],[-1.018,2.952],[0,4.178],[1.012,2.965],[1.911,1.551],[2.685,0]],"v":[[26.281,-4.295],[30.666,-11.069],[32.185,-21.792],[30.658,-32.459],[26.264,-39.213],[19.387,-41.549],[12.502,-39.223],[8.099,-32.468],[6.572,-21.792],[8.091,-11.078],[12.476,-4.304],[19.387,-1.959]],"c":true}},"nm":"0","hd":false},{"ty":"mm","mm":1,"nm":"Merge Paths 1","hd":false},{"ty":"st","c":{"a":0,"k":[0.541176470588,0.552941176471,0.968627510819,1]},"o":{"a":0,"k":100},"w":{"a":0,"k":1},"lc":1,"lj":1,"ml":4,"bm":0,"nm":"Stroke 1","hd":false},{"ty":"tr","p":{"a":0,"k":[0,0]},"a":{"a":0,"k":[0,0]},"s":{"a":0,"k":[100,100]},"r":{"a":0,"k":0},"o":{"a":0,"k":100},"sk":{"a":0,"k":0},"sa":{"a":0,"k":0},"nm":"Transform"}],"nm":"0","bm":0,"hd":false},{"ty":"tm","s":{"a":1,"k":[{"i":{"x":[0.433],"y":[1]},"o":{"x":[0.664],"y":[0]},"t":342,"s":[0]},{"t":353,"s":[100]}]},"e":{"a":1,"k":[{"i":{"x":[0.382],"y":[1]},"o":{"x":[0.752],"y":[0]},"t":337,"s":[0]},{"t":351,"s":[100]}]},"o":{"a":0,"k":0},"m":1,"nm":"Trim Paths 1","hd":false}],"ip":336,"op":354,"st":310,"ct":1,"bm":0},{"ddd":0,"ind":35,"ty":4,"nm":"0 stroke5","parent":41,"sr":1,"ks":{"o":{"a":0,"k":100},"r":{"a":0,"k":0},"p":{"a":0,"k":[20.037,-21.719,0]},"a":{"a":0,"k":[19.449,-21.877,0]},"s":{"a":0,"k":[196,152,100]}},"ao":0,"shapes":[{"ty":"gr","it":[{"ind":0,"ty":"sh","ks":{"a":0,"k":{"i":[[-1.911,1.557],[-1.012,2.958],[0,4.191],[1.018,2.946],[1.911,1.557],[2.673,0],[1.917,-1.551],[1.018,-2.952],[0,-4.165],[-1.012,-2.965],[-1.911,-1.551],[-2.696,0]],"o":[[1.911,-1.557],[1.012,-2.958],[0,-4.165],[-1.018,-2.946],[-1.911,-1.557],[-2.673,0],[-1.917,1.551],[-1.018,2.952],[0,4.178],[1.012,2.965],[1.911,1.551],[2.685,0]],"v":[[26.281,-4.295],[30.666,-11.069],[32.185,-21.792],[30.658,-32.459],[26.264,-39.213],[19.387,-41.549],[12.502,-39.223],[8.099,-32.468],[6.572,-21.792],[8.091,-11.078],[12.476,-4.304],[19.387,-1.959]],"c":true}},"nm":"0","hd":false},{"ty":"mm","mm":1,"nm":"Merge Paths 1","hd":false},{"ty":"st","c":{"a":0,"k":[0.541176470588,0.552941176471,0.968627510819,1]},"o":{"a":0,"k":100},"w":{"a":0,"k":1},"lc":1,"lj":1,"ml":4,"bm":0,"nm":"Stroke 1","hd":false},{"ty":"tr","p":{"a":0,"k":[0,0]},"a":{"a":0,"k":[0,0]},"s":{"a":0,"k":[100,100]},"r":{"a":0,"k":0},"o":{"a":0,"k":100},"sk":{"a":0,"k":0},"sa":{"a":0,"k":0},"nm":"Transform"}],"nm":"0","bm":0,"hd":false},{"ty":"tm","s":{"a":1,"k":[{"i":{"x":[0.433],"y":[1]},"o":{"x":[0.664],"y":[0]},"t":280,"s":[0]},{"t":291,"s":[100]}]},"e":{"a":1,"k":[{"i":{"x":[0.382],"y":[1]},"o":{"x":[0.752],"y":[0]},"t":275,"s":[0]},{"t":289,"s":[100]}]},"o":{"a":0,"k":0},"m":1,"nm":"Trim Paths 1","hd":false}],"ip":274,"op":292,"st":248,"ct":1,"bm":0},{"ddd":0,"ind":36,"ty":4,"nm":"0 stroke4","parent":41,"sr":1,"ks":{"o":{"a":0,"k":100},"r":{"a":0,"k":0},"p":{"a":0,"k":[20.037,-21.719,0]},"a":{"a":0,"k":[19.449,-21.877,0]},"s":{"a":0,"k":[196,152,100]}},"ao":0,"shapes":[{"ty":"gr","it":[{"ind":0,"ty":"sh","ks":{"a":0,"k":{"i":[[-1.911,1.557],[-1.012,2.958],[0,4.191],[1.018,2.946],[1.911,1.557],[2.673,0],[1.917,-1.551],[1.018,-2.952],[0,-4.165],[-1.012,-2.965],[-1.911,-1.551],[-2.696,0]],"o":[[1.911,-1.557],[1.012,-2.958],[0,-4.165],[-1.018,-2.946],[-1.911,-1.557],[-2.673,0],[-1.917,1.551],[-1.018,2.952],[0,4.178],[1.012,2.965],[1.911,1.551],[2.685,0]],"v":[[26.281,-4.295],[30.666,-11.069],[32.185,-21.792],[30.658,-32.459],[26.264,-39.213],[19.387,-41.549],[12.502,-39.223],[8.099,-32.468],[6.572,-21.792],[8.091,-11.078],[12.476,-4.304],[19.387,-1.959]],"c":true}},"nm":"0","hd":false},{"ty":"mm","mm":1,"nm":"Merge Paths 1","hd":false},{"ty":"st","c":{"a":0,"k":[0.541176470588,0.552941176471,0.968627510819,1]},"o":{"a":0,"k":100},"w":{"a":0,"k":1},"lc":1,"lj":1,"ml":4,"bm":0,"nm":"Stroke 1","hd":false},{"ty":"tr","p":{"a":0,"k":[0,0]},"a":{"a":0,"k":[0,0]},"s":{"a":0,"k":[100,100]},"r":{"a":0,"k":0},"o":{"a":0,"k":100},"sk":{"a":0,"k":0},"sa":{"a":0,"k":0},"nm":"Transform"}],"nm":"0","bm":0,"hd":false},{"ty":"tm","s":{"a":1,"k":[{"i":{"x":[0.433],"y":[1]},"o":{"x":[0.664],"y":[0]},"t":218,"s":[0]},{"t":229,"s":[100]}]},"e":{"a":1,"k":[{"i":{"x":[0.382],"y":[1]},"o":{"x":[0.752],"y":[0]},"t":213,"s":[0]},{"t":227,"s":[100]}]},"o":{"a":0,"k":0},"m":1,"nm":"Trim Paths 1","hd":false}],"ip":212,"op":230,"st":186,"ct":1,"bm":0},{"ddd":0,"ind":37,"ty":4,"nm":"0 stroke3","parent":41,"sr":1,"ks":{"o":{"a":0,"k":100},"r":{"a":0,"k":0},"p":{"a":0,"k":[20.037,-21.719,0]},"a":{"a":0,"k":[19.449,-21.877,0]},"s":{"a":0,"k":[196,152,100]}},"ao":0,"shapes":[{"ty":"gr","it":[{"ind":0,"ty":"sh","ks":{"a":0,"k":{"i":[[-1.911,1.557],[-1.012,2.958],[0,4.191],[1.018,2.946],[1.911,1.557],[2.673,0],[1.917,-1.551],[1.018,-2.952],[0,-4.165],[-1.012,-2.965],[-1.911,-1.551],[-2.696,0]],"o":[[1.911,-1.557],[1.012,-2.958],[0,-4.165],[-1.018,-2.946],[-1.911,-1.557],[-2.673,0],[-1.917,1.551],[-1.018,2.952],[0,4.178],[1.012,2.965],[1.911,1.551],[2.685,0]],"v":[[26.281,-4.295],[30.666,-11.069],[32.185,-21.792],[30.658,-32.459],[26.264,-39.213],[19.387,-41.549],[12.502,-39.223],[8.099,-32.468],[6.572,-21.792],[8.091,-11.078],[12.476,-4.304],[19.387,-1.959]],"c":true}},"nm":"0","hd":false},{"ty":"mm","mm":1,"nm":"Merge Paths 1","hd":false},{"ty":"st","c":{"a":0,"k":[0.541176470588,0.552941176471,0.968627510819,1]},"o":{"a":0,"k":100},"w":{"a":0,"k":1},"lc":1,"lj":1,"ml":4,"bm":0,"nm":"Stroke 1","hd":false},{"ty":"tr","p":{"a":0,"k":[0,0]},"a":{"a":0,"k":[0,0]},"s":{"a":0,"k":[100,100]},"r":{"a":0,"k":0},"o":{"a":0,"k":100},"sk":{"a":0,"k":0},"sa":{"a":0,"k":0},"nm":"Transform"}],"nm":"0","bm":0,"hd":false},{"ty":"tm","s":{"a":1,"k":[{"i":{"x":[0.433],"y":[1]},"o":{"x":[0.664],"y":[0]},"t":156,"s":[0]},{"t":167,"s":[100]}]},"e":{"a":1,"k":[{"i":{"x":[0.382],"y":[1]},"o":{"x":[0.752],"y":[0]},"t":151,"s":[0]},{"t":165,"s":[100]}]},"o":{"a":0,"k":0},"m":1,"nm":"Trim Paths 1","hd":false}],"ip":150,"op":168,"st":124,"ct":1,"bm":0},{"ddd":0,"ind":38,"ty":4,"nm":"0 stroke2","parent":41,"sr":1,"ks":{"o":{"a":0,"k":100},"r":{"a":0,"k":0},"p":{"a":0,"k":[20.037,-21.719,0]},"a":{"a":0,"k":[19.449,-21.877,0]},"s":{"a":0,"k":[196,152,100]}},"ao":0,"shapes":[{"ty":"gr","it":[{"ind":0,"ty":"sh","ks":{"a":0,"k":{"i":[[-1.911,1.557],[-1.012,2.958],[0,4.191],[1.018,2.946],[1.911,1.557],[2.673,0],[1.917,-1.551],[1.018,-2.952],[0,-4.165],[-1.012,-2.965],[-1.911,-1.551],[-2.696,0]],"o":[[1.911,-1.557],[1.012,-2.958],[0,-4.165],[-1.018,-2.946],[-1.911,-1.557],[-2.673,0],[-1.917,1.551],[-1.018,2.952],[0,4.178],[1.012,2.965],[1.911,1.551],[2.685,0]],"v":[[26.281,-4.295],[30.666,-11.069],[32.185,-21.792],[30.658,-32.459],[26.264,-39.213],[19.387,-41.549],[12.502,-39.223],[8.099,-32.468],[6.572,-21.792],[8.091,-11.078],[12.476,-4.304],[19.387,-1.959]],"c":true}},"nm":"0","hd":false},{"ty":"mm","mm":1,"nm":"Merge Paths 1","hd":false},{"ty":"st","c":{"a":0,"k":[0.541176470588,0.552941176471,0.968627510819,1]},"o":{"a":0,"k":100},"w":{"a":0,"k":1},"lc":1,"lj":1,"ml":4,"bm":0,"nm":"Stroke 1","hd":false},{"ty":"tr","p":{"a":0,"k":[0,0]},"a":{"a":0,"k":[0,0]},"s":{"a":0,"k":[100,100]},"r":{"a":0,"k":0},"o":{"a":0,"k":100},"sk":{"a":0,"k":0},"sa":{"a":0,"k":0},"nm":"Transform"}],"nm":"0","bm":0,"hd":false},{"ty":"tm","s":{"a":1,"k":[{"i":{"x":[0.433],"y":[1]},"o":{"x":[0.664],"y":[0]},"t":94,"s":[0]},{"t":105,"s":[100]}]},"e":{"a":1,"k":[{"i":{"x":[0.382],"y":[1]},"o":{"x":[0.752],"y":[0]},"t":89,"s":[0]},{"t":103,"s":[100]}]},"o":{"a":0,"k":0},"m":1,"nm":"Trim Paths 1","hd":false}],"ip":88,"op":106,"st":62,"ct":1,"bm":0},{"ddd":0,"ind":39,"ty":4,"nm":"0 stroke","parent":41,"sr":1,"ks":{"o":{"a":0,"k":100},"r":{"a":0,"k":0},"p":{"a":0,"k":[20.037,-21.719,0]},"a":{"a":0,"k":[19.449,-21.877,0]},"s":{"a":0,"k":[196,152,100]}},"ao":0,"shapes":[{"ty":"gr","it":[{"ind":0,"ty":"sh","ks":{"a":0,"k":{"i":[[-1.911,1.557],[-1.012,2.958],[0,4.191],[1.018,2.946],[1.911,1.557],[2.673,0],[1.917,-1.551],[1.018,-2.952],[0,-4.165],[-1.012,-2.965],[-1.911,-1.551],[-2.696,0]],"o":[[1.911,-1.557],[1.012,-2.958],[0,-4.165],[-1.018,-2.946],[-1.911,-1.557],[-2.673,0],[-1.917,1.551],[-1.018,2.952],[0,4.178],[1.012,2.965],[1.911,1.551],[2.685,0]],"v":[[26.281,-4.295],[30.666,-11.069],[32.185,-21.792],[30.658,-32.459],[26.264,-39.213],[19.387,-41.549],[12.502,-39.223],[8.099,-32.468],[6.572,-21.792],[8.091,-11.078],[12.476,-4.304],[19.387,-1.959]],"c":true}},"nm":"0","hd":false},{"ty":"mm","mm":1,"nm":"Merge Paths 1","hd":false},{"ty":"st","c":{"a":0,"k":[0.541176470588,0.552941176471,0.968627510819,1]},"o":{"a":0,"k":100},"w":{"a":0,"k":1},"lc":1,"lj":1,"ml":4,"bm":0,"nm":"Stroke 1","hd":false},{"ty":"tr","p":{"a":0,"k":[0,0]},"a":{"a":0,"k":[0,0]},"s":{"a":0,"k":[100,100]},"r":{"a":0,"k":0},"o":{"a":0,"k":100},"sk":{"a":0,"k":0},"sa":{"a":0,"k":0},"nm":"Transform"}],"nm":"0","bm":0,"hd":false},{"ty":"tm","s":{"a":1,"k":[{"i":{"x":[0.433],"y":[1]},"o":{"x":[0.664],"y":[0]},"t":32,"s":[0]},{"t":43,"s":[100]}]},"e":{"a":1,"k":[{"i":{"x":[0.382],"y":[1]},"o":{"x":[0.752],"y":[0]},"t":27,"s":[0]},{"t":41,"s":[100]}]},"o":{"a":0,"k":0},"m":1,"nm":"Trim Paths 1","hd":false}],"ip":26,"op":44,"st":0,"ct":1,"bm":0},{"ddd":0,"ind":40,"ty":4,"nm":"0","sr":1,"ks":{"o":{"a":0,"k":100},"r":{"a":0,"k":0},"p":{"a":0,"k":[323.537,908.406,0]},"a":{"a":0,"k":[19.037,-21.594,0]},"s":{"a":1,"k":[{"i":{"x":[0.833,0.833,0.833],"y":[0.833,0.833,0.833]},"o":{"x":[0.167,0.167,0.167],"y":[0.167,0.167,0.167]},"t":30,"s":[100,100,100]},{"i":{"x":[0.667,0.667,0.667],"y":[1,1,1]},"o":{"x":[0.167,0.167,0.167],"y":[0.167,0.167,0]},"t":34,"s":[115,115,100]},{"i":{"x":[0.833,0.833,0.833],"y":[1,1,1]},"o":{"x":[0.167,0.167,0.167],"y":[0,0,0]},"t":51,"s":[100,100,100]},{"i":{"x":[0.833,0.833,0.833],"y":[0.833,0.833,0.833]},"o":{"x":[0.167,0.167,0.167],"y":[0.167,0.167,0.167]},"t":91,"s":[100,100,100]},{"i":{"x":[0.667,0.667,0.667],"y":[1,1,1]},"o":{"x":[0.167,0.167,0.167],"y":[0.167,0.167,0]},"t":95,"s":[115,115,100]},{"i":{"x":[0.833,0.833,0.833],"y":[1,1,1]},"o":{"x":[0.167,0.167,0.167],"y":[0,0,0]},"t":112,"s":[100,100,100]},{"i":{"x":[0.833,0.833,0.833],"y":[0.833,0.833,0.833]},"o":{"x":[0.167,0.167,0.167],"y":[0.167,0.167,0.167]},"t":152,"s":[100,100,100]},{"i":{"x":[0.667,0.667,0.667],"y":[1,1,1]},"o":{"x":[0.167,0.167,0.167],"y":[0.167,0.167,0]},"t":156,"s":[115,115,100]},{"i":{"x":[0.833,0.833,0.833],"y":[1,1,1]},"o":{"x":[0.167,0.167,0.167],"y":[0,0,0]},"t":173,"s":[100,100,100]},{"i":{"x":[0.833,0.833,0.833],"y":[0.833,0.833,0.833]},"o":{"x":[0.167,0.167,0.167],"y":[0.167,0.167,0.167]},"t":214,"s":[100,100,100]},{"i":{"x":[0.667,0.667,0.667],"y":[1,1,1]},"o":{"x":[0.167,0.167,0.167],"y":[0.167,0.167,0]},"t":218,"s":[115,115,100]},{"i":{"x":[0.833,0.833,0.833],"y":[1,1,1]},"o":{"x":[0.167,0.167,0.167],"y":[0,0,0]},"t":235,"s":[100,100,100]},{"i":{"x":[0.833,0.833,0.833],"y":[0.833,0.833,0.833]},"o":{"x":[0.167,0.167,0.167],"y":[0.167,0.167,0.167]},"t":276,"s":[100,100,100]},{"i":{"x":[0.667,0.667,0.667],"y":[1,1,1]},"o":{"x":[0.167,0.167,0.167],"y":[0.167,0.167,0]},"t":280,"s":[115,115,100]},{"i":{"x":[0.833,0.833,0.833],"y":[1,1,1]},"o":{"x":[0.167,0.167,0.167],"y":[0,0,0]},"t":297,"s":[100,100,100]},{"i":{"x":[0.833,0.833,0.833],"y":[0.833,0.833,0.833]},"o":{"x":[0.167,0.167,0.167],"y":[0.167,0.167,0.167]},"t":338,"s":[100,100,100]},{"i":{"x":[0.667,0.667,0.667],"y":[1,1,1]},"o":{"x":[0.167,0.167,0.167],"y":[0.167,0.167,0]},"t":342,"s":[115,115,100]},{"i":{"x":[0.833,0.833,0.833],"y":[1,1,1]},"o":{"x":[0.167,0.167,0.167],"y":[0,0,0]},"t":359,"s":[100,100,100]},{"i":{"x":[0.833,0.833,0.833],"y":[0.833,0.833,0.833]},"o":{"x":[0.167,0.167,0.167],"y":[0.167,0.167,0.167]},"t":400,"s":[100,100,100]},{"i":{"x":[0.667,0.667,0.667],"y":[1,1,1]},"o":{"x":[0.167,0.167,0.167],"y":[0.167,0.167,0]},"t":404,"s":[115,115,100]},{"t":421,"s":[100,100,100]}]}},"ao":0,"shapes":[{"ty":"gr","it":[{"ind":0,"ty":"sh","ks":{"a":0,"k":{"i":[[-2.386,1.768],[-1.264,3.359],[0,4.759],[1.271,3.345],[2.386,1.768],[3.338,0],[2.393,-1.761],[1.271,-3.352],[0,-4.73],[-1.264,-3.366],[-2.386,-1.761],[-3.366,-0.014]],"o":[[2.386,-1.768],[1.264,-3.359],[0,-4.73],[-1.271,-3.345],[-2.386,-1.768],[-3.338,0],[-2.394,1.761],[-1.271,3.352],[0,4.744],[1.264,3.366],[2.386,1.761],[3.352,0]],"v":[[27.997,-1.928],[33.473,-9.62],[35.369,-21.797],[33.462,-33.91],[27.976,-41.58],[19.389,-44.233],[10.792,-41.591],[5.295,-33.92],[3.388,-21.797],[5.284,-9.631],[10.76,-1.939],[19.389,0.724]],"c":true}},"nm":"0","hd":false},{"ind":1,"ty":"sh","ks":{"a":0,"k":{"i":[[1.406,1.286],[0.76,2.507],[0,3.636],[-1.676,2.898],[-2.94,0],[-1.414,-1.3],[-0.76,-2.507],[0,-3.622],[1.669,-2.883],[2.954,0]],"o":[[-1.406,-1.285],[-0.76,-2.507],[0.014,-5.44],[1.676,-2.898],[1.946,0],[1.413,1.3],[0.76,2.507],[0,5.455],[-1.669,2.884],[-1.975,0]],"v":[[14.318,-6.893],[11.069,-12.582],[9.929,-21.797],[12.464,-34.304],[19.389,-38.651],[24.428,-36.701],[27.688,-30.991],[28.828,-21.797],[26.325,-9.29],[19.389,-4.964]],"c":true}},"nm":"0","hd":false},{"ty":"mm","mm":1,"nm":"Merge Paths 1","hd":false},{"ty":"fl","c":{"a":0,"k":[1,1,1,1]},"o":{"a":0,"k":100},"r":1,"bm":0,"nm":"Fill 1","hd":false},{"ty":"st","c":{"a":0,"k":[0,0,0,1]},"o":{"a":0,"k":100},"w":{"a":0,"k":0.01},"lc":1,"lj":1,"ml":4,"bm":0,"nm":"Stroke 1","hd":false},{"ty":"tr","p":{"a":0,"k":[0,0]},"a":{"a":0,"k":[0,0]},"s":{"a":0,"k":[100,100]},"r":{"a":0,"k":0},"o":{"a":0,"k":100},"sk":{"a":0,"k":0},"sa":{"a":0,"k":0},"nm":"Transform"}],"nm":"0","bm":0,"hd":false}],"ip":0,"op":775,"st":0,"ct":1,"bm":0},{"ddd":0,"ind":41,"ty":4,"nm":"0 shine","sr":1,"ks":{"o":{"a":1,"k":[{"i":{"x":[0.833],"y":[0.833]},"o":{"x":[0.167],"y":[0.167]},"t":35,"s":[0]},{"i":{"x":[0.833],"y":[0.833]},"o":{"x":[0.167],"y":[0.167]},"t":43,"s":[100]},{"i":{"x":[0.833],"y":[0.833]},"o":{"x":[0.167],"y":[0.167]},"t":58,"s":[0]},{"i":{"x":[0.833],"y":[0.833]},"o":{"x":[0.167],"y":[0.167]},"t":95,"s":[0]},{"i":{"x":[0.833],"y":[0.833]},"o":{"x":[0.167],"y":[0.167]},"t":103,"s":[100]},{"i":{"x":[0.833],"y":[0.833]},"o":{"x":[0.167],"y":[0.167]},"t":118,"s":[0]},{"i":{"x":[0.833],"y":[0.833]},"o":{"x":[0.167],"y":[0.167]},"t":156,"s":[0]},{"i":{"x":[0.833],"y":[0.833]},"o":{"x":[0.167],"y":[0.167]},"t":164,"s":[100]},{"i":{"x":[0.833],"y":[0.833]},"o":{"x":[0.167],"y":[0.167]},"t":179,"s":[0]},{"i":{"x":[0.833],"y":[0.833]},"o":{"x":[0.167],"y":[0.167]},"t":218,"s":[0]},{"i":{"x":[0.833],"y":[0.833]},"o":{"x":[0.167],"y":[0.167]},"t":226,"s":[100]},{"i":{"x":[0.833],"y":[0.833]},"o":{"x":[0.167],"y":[0.167]},"t":241,"s":[0]},{"i":{"x":[0.833],"y":[0.833]},"o":{"x":[0.167],"y":[0.167]},"t":280,"s":[0]},{"i":{"x":[0.833],"y":[0.833]},"o":{"x":[0.167],"y":[0.167]},"t":288,"s":[100]},{"i":{"x":[0.833],"y":[0.833]},"o":{"x":[0.167],"y":[0.167]},"t":303,"s":[0]},{"i":{"x":[0.833],"y":[0.833]},"o":{"x":[0.167],"y":[0.167]},"t":342,"s":[0]},{"i":{"x":[0.833],"y":[0.833]},"o":{"x":[0.167],"y":[0.167]},"t":350,"s":[100]},{"i":{"x":[0.833],"y":[0.833]},"o":{"x":[0.167],"y":[0.167]},"t":365,"s":[0]},{"i":{"x":[0.833],"y":[0.833]},"o":{"x":[0.167],"y":[0.167]},"t":404,"s":[0]},{"i":{"x":[0.833],"y":[0.833]},"o":{"x":[0.167],"y":[0.167]},"t":412,"s":[100]},{"t":427,"s":[0]}]},"r":{"a":0,"k":0},"p":{"a":0,"k":[323.537,908.406,0]},"a":{"a":0,"k":[19.037,-21.594,0]},"s":{"a":1,"k":[{"i":{"x":[0.833,0.833,0.833],"y":[0.833,0.833,0.833]},"o":{"x":[0.167,0.167,0.167],"y":[0.167,0.167,0.167]},"t":30,"s":[100,100,100]},{"i":{"x":[0.667,0.667,0.667],"y":[1,1,1]},"o":{"x":[0.167,0.167,0.167],"y":[0.167,0.167,0]},"t":34,"s":[115,115,100]},{"i":{"x":[0.833,0.833,0.833],"y":[1,1,1]},"o":{"x":[0.167,0.167,0.167],"y":[0,0,0]},"t":51,"s":[100,100,100]},{"i":{"x":[0.833,0.833,0.833],"y":[0.833,0.833,0.833]},"o":{"x":[0.167,0.167,0.167],"y":[0.167,0.167,0.167]},"t":91,"s":[100,100,100]},{"i":{"x":[0.667,0.667,0.667],"y":[1,1,1]},"o":{"x":[0.167,0.167,0.167],"y":[0.167,0.167,0]},"t":95,"s":[115,115,100]},{"i":{"x":[0.833,0.833,0.833],"y":[1,1,1]},"o":{"x":[0.167,0.167,0.167],"y":[0,0,0]},"t":112,"s":[100,100,100]},{"i":{"x":[0.833,0.833,0.833],"y":[0.833,0.833,0.833]},"o":{"x":[0.167,0.167,0.167],"y":[0.167,0.167,0.167]},"t":152,"s":[100,100,100]},{"i":{"x":[0.667,0.667,0.667],"y":[1,1,1]},"o":{"x":[0.167,0.167,0.167],"y":[0.167,0.167,0]},"t":156,"s":[115,115,100]},{"i":{"x":[0.833,0.833,0.833],"y":[1,1,1]},"o":{"x":[0.167,0.167,0.167],"y":[0,0,0]},"t":173,"s":[100,100,100]},{"i":{"x":[0.833,0.833,0.833],"y":[0.833,0.833,0.833]},"o":{"x":[0.167,0.167,0.167],"y":[0.167,0.167,0.167]},"t":214,"s":[100,100,100]},{"i":{"x":[0.667,0.667,0.667],"y":[1,1,1]},"o":{"x":[0.167,0.167,0.167],"y":[0.167,0.167,0]},"t":218,"s":[115,115,100]},{"i":{"x":[0.833,0.833,0.833],"y":[1,1,1]},"o":{"x":[0.167,0.167,0.167],"y":[0,0,0]},"t":235,"s":[100,100,100]},{"i":{"x":[0.833,0.833,0.833],"y":[0.833,0.833,0.833]},"o":{"x":[0.167,0.167,0.167],"y":[0.167,0.167,0.167]},"t":276,"s":[100,100,100]},{"i":{"x":[0.667,0.667,0.667],"y":[1,1,1]},"o":{"x":[0.167,0.167,0.167],"y":[0.167,0.167,0]},"t":280,"s":[115,115,100]},{"i":{"x":[0.833,0.833,0.833],"y":[1,1,1]},"o":{"x":[0.167,0.167,0.167],"y":[0,0,0]},"t":297,"s":[100,100,100]},{"i":{"x":[0.833,0.833,0.833],"y":[0.833,0.833,0.833]},"o":{"x":[0.167,0.167,0.167],"y":[0.167,0.167,0.167]},"t":338,"s":[100,100,100]},{"i":{"x":[0.667,0.667,0.667],"y":[1,1,1]},"o":{"x":[0.167,0.167,0.167],"y":[0.167,0.167,0]},"t":342,"s":[115,115,100]},{"i":{"x":[0.833,0.833,0.833],"y":[1,1,1]},"o":{"x":[0.167,0.167,0.167],"y":[0,0,0]},"t":359,"s":[100,100,100]},{"i":{"x":[0.833,0.833,0.833],"y":[0.833,0.833,0.833]},"o":{"x":[0.167,0.167,0.167],"y":[0.167,0.167,0.167]},"t":400,"s":[100,100,100]},{"i":{"x":[0.667,0.667,0.667],"y":[1,1,1]},"o":{"x":[0.167,0.167,0.167],"y":[0.167,0.167,0]},"t":404,"s":[115,115,100]},{"t":421,"s":[100,100,100]}]}},"ao":0,"ef":[{"ty":29,"nm":"Gaussian Blur","np":5,"mn":"ADBE Gaussian Blur 2","ix":1,"en":1,"ef":[{"ty":0,"nm":"Blurriness","mn":"ADBE Gaussian Blur 2-0001","ix":1,"v":{"a":0,"k":14.8}},{"ty":7,"nm":"Blur Dimensions","mn":"ADBE Gaussian Blur 2-0002","ix":2,"v":{"a":0,"k":1}},{"ty":7,"nm":"Repeat Edge Pixels","mn":"ADBE Gaussian Blur 2-0003","ix":3,"v":{"a":0,"k":0}}]}],"shapes":[{"ty":"gr","it":[{"ind":0,"ty":"sh","ks":{"a":0,"k":{"i":[[-2.386,1.768],[-1.264,3.359],[0,4.759],[1.271,3.345],[2.386,1.768],[3.338,0],[2.393,-1.761],[1.271,-3.352],[0,-4.73],[-1.264,-3.366],[-2.386,-1.761],[-3.366,-0.014]],"o":[[2.386,-1.768],[1.264,-3.359],[0,-4.73],[-1.271,-3.345],[-2.386,-1.768],[-3.338,0],[-2.394,1.761],[-1.271,3.352],[0,4.744],[1.264,3.366],[2.386,1.761],[3.352,0]],"v":[[27.997,-1.928],[33.473,-9.62],[35.369,-21.797],[33.462,-33.91],[27.976,-41.58],[19.389,-44.233],[10.792,-41.591],[5.295,-33.92],[3.388,-21.797],[5.284,-9.631],[10.76,-1.939],[19.389,0.724]],"c":true}},"nm":"0","hd":false},{"ind":1,"ty":"sh","ks":{"a":0,"k":{"i":[[1.406,1.286],[0.76,2.507],[0,3.636],[-1.676,2.898],[-2.94,0],[-1.414,-1.3],[-0.76,-2.507],[0,-3.622],[1.669,-2.883],[2.954,0]],"o":[[-1.406,-1.285],[-0.76,-2.507],[0.014,-5.44],[1.676,-2.898],[1.946,0],[1.413,1.3],[0.76,2.507],[0,5.455],[-1.669,2.884],[-1.975,0]],"v":[[14.318,-6.893],[11.069,-12.582],[9.929,-21.797],[12.464,-34.304],[19.389,-38.651],[24.428,-36.701],[27.688,-30.991],[28.828,-21.797],[26.325,-9.29],[19.389,-4.964]],"c":true}},"nm":"0","hd":false},{"ty":"mm","mm":1,"nm":"Merge Paths 1","hd":false},{"ty":"fl","c":{"a":0,"k":[1,1,1,1]},"o":{"a":0,"k":100},"r":1,"bm":0,"nm":"Fill 1","hd":false},{"ty":"st","c":{"a":0,"k":[0,0,0,1]},"o":{"a":0,"k":100},"w":{"a":0,"k":0.01},"lc":1,"lj":1,"ml":4,"bm":0,"nm":"Stroke 1","hd":false},{"ty":"tr","p":{"a":0,"k":[0,0]},"a":{"a":0,"k":[0,0]},"s":{"a":0,"k":[100,100]},"r":{"a":0,"k":0},"o":{"a":0,"k":100},"sk":{"a":0,"k":0},"sa":{"a":0,"k":0},"nm":"Transform"}],"nm":"0","bm":0,"hd":false}],"ip":0,"op":775,"st":0,"ct":1,"bm":0},{"ddd":0,"ind":42,"ty":4,"nm":"Shape Layer 1","sr":1,"ks":{"o":{"a":0,"k":100},"r":{"a":0,"k":0},"p":{"a":0,"k":[960,640,0]},"a":{"a":0,"k":[0,0,0]},"s":{"a":0,"k":[100,100,100]}},"ao":0,"shapes":[{"ty":"gr","it":[{"ind":0,"ty":"sh","ks":{"a":0,"k":{"i":[[0,0],[0,0]],"o":[[0,0],[0,0]],"v":[[-652,196],[648,196]],"c":false}},"nm":"Path 1","hd":false},{"ty":"st","c":{"a":0,"k":[0.231372563979,0.211764720842,0.423529441684,1]},"o":{"a":0,"k":100},"w":{"a":0,"k":6},"lc":1,"lj":1,"ml":4,"bm":0,"nm":"Stroke 1","hd":false},{"ty":"fl","c":{"a":0,"k":[0,0,0,1]},"o":{"a":0,"k":100},"r":1,"bm":0,"nm":"Fill 1","hd":false},{"ty":"tr","p":{"a":0,"k":[0,0]},"a":{"a":0,"k":[0,0]},"s":{"a":0,"k":[100,100]},"r":{"a":0,"k":0},"o":{"a":0,"k":100},"sk":{"a":0,"k":0},"sa":{"a":0,"k":0},"nm":"Transform"}],"nm":"Shape 1","bm":0,"hd":false}],"ip":0,"op":775,"st":0,"ct":1,"bm":0}],"markers":[],"chars":[{"ch":"c","size":30,"style":"Medium","w":56.78,"data":{"shapes":[{"ty":"gr","it":[{"ind":0,"ty":"sh","ks":{"a":0,"k":{"i":[[-3.208,1.586],[-1.918,2.77],[-0.379,3.528],[0,0],[1.124,-1.397],[1.645,-0.746],[2.012,0],[2.213,1.586],[1.207,2.889],[0,3.977],[-1.231,2.853],[-2.214,1.551],[-2.96,0],[-2.024,-1.847],[-0.568,-2.557],[0,0],[2,2.747],[3.243,1.527],[4.143,0],[3.788,-2.391],[2.083,-4.249],[0,-5.54],[-2.036,-4.238],[-3.8,-2.403],[-5.28,0]],"o":[[3.208,-1.586],[1.918,-2.77],[0,0],[-0.45,1.965],[-1.125,1.397],[-1.646,0.746],[-3.007,0],[-2.214,-1.586],[-1.207,-2.888],[0,-3.882],[1.231,-2.853],[2.213,-1.55],[3.385,0],[2.024,1.847],[0,0],[-0.379,-3.669],[-2.001,-2.746],[-3.244,-1.527],[-5.137,0],[-3.788,2.391],[-2.084,4.25],[0,5.469],[2.036,4.238],[3.8,2.403],[4.309,0]],"v":[[41.389,-1.278],[49.077,-7.812],[52.521,-17.259],[42.188,-17.259],[39.826,-12.216],[35.671,-9.002],[30.185,-7.884],[22.354,-10.263],[17.223,-16.974],[15.412,-27.273],[17.259,-37.376],[22.425,-43.981],[30.185,-46.307],[38.299,-43.537],[42.188,-36.932],[52.521,-36.932],[48.952,-46.555],[41.087,-52.965],[30.007,-55.256],[16.619,-51.669],[7.812,-41.708],[4.688,-27.024],[7.741,-12.464],[16.495,-2.504],[30.114,1.101]],"c":true}},"nm":"c","hd":false}],"nm":"c","bm":0,"hd":false}]},"fFamily":"Inter"},{"ch":"u","size":30,"style":"Medium","w":59.45,"data":{"shapes":[{"ty":"gr","it":[{"ind":0,"ty":"sh","ks":{"a":0,"k":{"i":[[1.314,-2.012],[1.976,-0.994],[1.989,0],[2.06,2.202],[0,3.717],[0,0],[0,0],[0,0],[-1.527,-3.054],[-2.687,-1.55],[-3.504,0],[-2.758,1.93],[-1.255,2.912],[0,0],[0,0],[0,0],[0,0],[0,0],[0,0]],"o":[[-1.314,2.012],[-1.977,0.994],[-3.291,0],[-2.06,-2.202],[0,0],[0,0],[0,0],[0,4.498],[1.527,3.054],[2.687,1.551],[4.095,0],[2.758,-1.929],[0,0],[0,0],[0,0],[0,0],[0,0],[0,0],[0.023,3.102]],"v":[[39.755,-14.95],[34.819,-10.44],[28.871,-8.949],[20.845,-12.251],[17.756,-21.129],[17.756,-54.545],[7.138,-54.545],[7.138,-19.851],[9.428,-8.523],[15.749,-1.616],[25.036,0.71],[35.316,-2.184],[41.335,-9.446],[41.903,-9.446],[41.903,0],[52.344,0],[52.344,-54.545],[41.69,-54.545],[41.69,-22.621]],"c":true}},"nm":"u","hd":false}],"nm":"u","bm":0,"hd":false}]},"fFamily":"Inter"},{"ch":"r","size":30,"style":"Medium","w":38.42,"data":{"shapes":[{"ty":"gr","it":[{"ind":0,"ty":"sh","ks":{"a":0,"k":{"i":[[0,0],[0,0],[-1.136,1.859],[-1.953,1.054],[-2.51,0],[-1.089,-0.154],[-0.426,-0.118],[0,0],[0.911,0.048],[0.663,0],[2.521,-1.692],[0.994,-2.935],[0,0],[0,0],[0,0],[0,0]],"o":[[0,0],[0,-2.367],[1.136,-1.858],[1.953,-1.053],[1.089,0],[1.089,0.154],[0,0],[-0.521,-0.071],[-0.912,-0.047],[-3.196,0],[-2.521,1.693],[0,0],[0,0],[0,0],[0,0],[0,0]],"v":[[17.756,0],[17.756,-33.31],[19.46,-39.648],[24.094,-44.016],[30.788,-45.597],[34.055,-45.366],[36.328,-44.957],[36.328,-55.114],[34.18,-55.291],[31.818,-55.362],[23.242,-52.823],[17.969,-45.881],[17.401,-45.881],[17.401,-54.545],[7.138,-54.545],[7.138,0]],"c":true}},"nm":"r","hd":false}],"nm":"r","bm":0,"hd":false}]},"fFamily":"Inter"},{"ch":"e","size":30,"style":"Medium","w":58.74,"data":{"shapes":[{"ty":"gr","it":[{"ind":0,"ty":"sh","ks":{"a":0,"k":{"i":[[-3.113,1.219],[-2.072,2.214],[-0.805,2.96],[0,0],[1.207,-1.16],[1.657,-0.58],[2.012,0],[2.32,1.338],[1.29,2.557],[0,3.646],[0,0],[-1.196,2.332],[-2.214,1.456],[-2.983,0],[-2.048,-1.255],[-1.136,-2.166],[0,-2.793],[0,0],[0,0],[0,0],[0,0],[1.326,3.468],[2.296,2.178],[2.888,1.018],[3.077,0],[3.776,-2.391],[2.095,-4.261],[0,-5.587],[-2.095,-4.202],[-3.871,-2.308],[-5.374,0]],"o":[[3.113,-1.219],[2.071,-2.213],[0,0],[-0.639,1.705],[-1.207,1.16],[-1.657,0.58],[-3.102,0],[-2.32,-1.337],[-1.291,-2.557],[0,0],[0,-2.722],[1.195,-2.332],[2.213,-1.456],[2.746,0],[2.047,1.255],[1.136,2.166],[0,0],[0,0],[0,0],[0,0],[0,-4.948],[-1.326,-3.468],[-2.297,-2.178],[-2.889,-1.018],[-5.066,0],[-3.776,2.391],[-2.095,4.261],[0,5.659],[2.095,4.203],[3.871,2.308],[3.977,0]],"v":[[41.282,-0.728],[49.059,-5.877],[53.374,-13.636],[43.324,-15.447],[40.554,-11.151],[36.257,-8.54],[30.753,-7.67],[22.621,-9.677],[17.205,-15.518],[15.27,-24.822],[15.27,-31.037],[17.063,-38.619],[22.177,-44.3],[29.972,-46.484],[37.163,-44.602],[41.939,-39.471],[43.643,-32.031],[10.689,-32.031],[10.689,-24.077],[54.048,-24.077],[54.048,-27.841],[52.06,-40.465],[46.626,-48.935],[38.849,-53.729],[29.901,-55.256],[16.637,-51.669],[7.83,-41.69],[4.688,-26.918],[7.83,-12.127],[16.779,-2.362],[30.646,1.101]],"c":true}},"nm":"e","hd":false}],"nm":"e","bm":0,"hd":false}]},"fFamily":"Inter"},{"ch":"n","size":30,"style":"Medium","w":59.73,"data":{"shapes":[{"ty":"gr","it":[{"ind":0,"ty":"sh","ks":{"a":0,"k":{"i":[[-1.101,2.048],[-1.906,1.065],[-2.462,0],[-2.06,-2.237],[0,-3.953],[0,0],[0,0],[0,0],[1.539,3.054],[2.793,1.551],[3.716,0],[2.687,-1.752],[1.255,-2.888],[0,0],[0,0],[0,0],[0,0],[0,0],[0,0]],"o":[[1.101,-2.047],[1.905,-1.065],[3.598,0],[2.06,2.237],[0,0],[0,0],[0,0],[0,-4.498],[-1.539,-3.054],[-2.794,-1.55],[-4.096,0],[-2.687,1.752],[0,0],[0,0],[0,0],[0,0],[0,0],[0,0],[0,-2.888]],"v":[[19.407,-39.79],[23.917,-44.46],[30.469,-46.058],[38.956,-42.702],[42.045,-33.416],[42.045,0],[52.663,0],[52.663,-34.695],[50.355,-46.023],[43.857,-52.93],[34.091,-55.256],[23.917,-52.628],[18.004,-45.668],[17.33,-45.668],[17.33,-54.545],[7.138,-54.545],[7.138,0],[17.756,0],[17.756,-32.386]],"c":true}},"nm":"n","hd":false}],"nm":"n","bm":0,"hd":false}]},"fFamily":"Inter"},{"ch":"t","size":30,"style":"Medium","w":37.18,"data":{"shapes":[{"ty":"gr","it":[{"ind":0,"ty":"sh","ks":{"a":0,"k":{"i":[[0,0],[0,0],[0,0],[0,0]],"o":[[0,0],[0,0],[0,0],[0,0]],"v":[[2.805,-54.545],[2.805,-46.023],[32.599,-46.023],[32.599,-54.545]],"c":true}},"nm":"t","hd":false},{"ind":1,"ty":"sh","ks":{"a":0,"k":{"i":[[0,0],[-1.491,-2.178],[-2.415,-1.041],[-2.794,0.047],[-1.136,0.249],[-0.616,0.237],[0,0],[0.639,-0.118],[0.852,0],[0.982,0.367],[0.615,1.03],[0,2.06],[0,0],[0,0]],"o":[[0,3.291],[1.491,2.178],[2.415,1.041],[1.705,-0.024],[1.136,-0.249],[0,0],[-0.355,0.071],[-0.639,0.119],[-1.16,0],[-0.983,-0.367],[-0.616,-1.03],[0,0],[0,0],[0,0]],"v":[[10.795,-13.814],[13.033,-5.611],[18.892,-0.781],[26.705,0.71],[30.966,0.302],[33.594,-0.426],[31.676,-9.197],[30.185,-8.913],[27.947,-8.736],[24.734,-9.286],[22.337,-11.381],[21.413,-16.016],[21.413,-67.614],[10.795,-67.614]],"c":true}},"nm":"t","hd":false}],"nm":"t","bm":0,"hd":false}]},"fFamily":"Inter"},{"ch":" ","size":30,"style":"Medium","w":26.49,"data":{},"fFamily":"Inter"},{"ch":"\r","size":30,"style":"Medium","w":0,"fFamily":"Inter"},{"ch":"p","size":30,"style":"Medium","w":61.72,"data":{"shapes":[{"ty":"gr","it":[{"ind":0,"ty":"sh","ks":{"a":0,"k":{"i":[[0,0],[0,0],[0,0],[-1.184,-1.491],[-2.095,-1.113],[-3.315,0],[-3.433,2.261],[-1.965,4.203],[0,5.895],[1.976,4.19],[3.456,2.226],[4.403,0],[2.06,-1.124],[1.16,-1.491],[0.615,-1.136],[0,0],[0,0],[0,0],[0,0]],"o":[[0,0],[0,0],[0.639,1.16],[1.184,1.491],[2.095,1.113],[4.403,0],[3.432,-2.261],[1.965,-4.202],[0,-5.895],[-1.977,-4.19],[-3.457,-2.225],[-3.386,0],[-2.06,1.125],[-1.16,1.491],[0,0],[0,0],[0,0],[0,0],[0,0]],"v":[[17.756,20.455],[17.756,-8.487],[18.395,-8.487],[21.129,-4.51],[26.048,-0.604],[34.162,1.065],[45.916,-2.326],[54.013,-12.021],[56.96,-27.166],[53.995,-42.294],[45.845,-51.918],[34.055,-55.256],[25.888,-53.569],[21.058,-49.645],[18.395,-45.703],[17.507,-45.703],[17.507,-54.545],[7.138,-54.545],[7.138,20.455]],"c":true}},"nm":"p","hd":false},{"ind":1,"ty":"sh","ks":{"a":0,"k":{"i":[[-1.089,2.841],[-2.119,1.586],[-3.078,0],[-2.143,-1.657],[-1.078,-2.864],[0,-3.598],[1.101,-2.912],[2.131,-1.692],[3.172,0],[2.107,1.622],[1.113,2.889],[0,3.835]],"o":[[1.089,-2.841],[2.118,-1.586],[3.196,0],[2.142,1.657],[1.077,2.865],[0,3.646],[-1.101,2.912],[-2.131,1.693],[-3.054,0],[-2.107,-1.621],[-1.113,-2.888],[0,-3.788]],"v":[[19.176,-37.216],[23.988,-43.857],[31.783,-46.236],[39.79,-43.75],[44.62,-36.967],[46.236,-27.273],[44.585,-17.436],[39.737,-10.529],[31.783,-7.99],[24.041,-10.423],[19.212,-17.188],[17.543,-27.273]],"c":true}},"nm":"p","hd":false}],"nm":"p","bm":0,"hd":false}]},"fFamily":"Inter"},{"ch":"i","size":30,"style":"Medium","w":24.89,"data":{"shapes":[{"ty":"gr","it":[{"ind":0,"ty":"sh","ks":{"a":0,"k":{"i":[[0,0],[0,0],[0,0],[0,0]],"o":[[0,0],[0,0],[0,0],[0,0]],"v":[[17.756,0],[17.756,-54.545],[7.138,-54.545],[7.138,0]],"c":true}},"nm":"i","hd":false},{"ind":1,"ty":"sh","ks":{"a":0,"k":{"i":[[-1.314,1.243],[0,1.728],[1.314,1.243],[1.847,0],[1.314,-1.243],[0,-1.752],[-1.314,-1.243],[-1.847,0]],"o":[[1.314,-1.243],[0,-1.752],[-1.314,-1.243],[-1.847,0],[-1.314,1.243],[0,1.728],[1.314,1.243],[1.847,0]],"v":[[17.241,-64.826],[19.212,-69.283],[17.241,-73.775],[12.5,-75.639],[7.759,-73.775],[5.788,-69.283],[7.759,-64.826],[12.5,-62.962]],"c":true}},"nm":"i","hd":false}],"nm":"i","bm":0,"hd":false}]},"fFamily":"Inter"}]}